Workbook

Sheet Export Summary
B3: This document was exported from Numbers. Each table was converted to an Excel worksheet. All other objects on each Numbers sheet were placed on separate worksheets. Please be aware that formula calculations may differ in Excel.
B7: Numbers Sheet Name | C7: Numbers Table Name | D7: Excel Worksheet Name
B9: Project Detail
C10: Table 1 | D10: Project Detail
B11: Project Detail
C12: Table 1 | D12: Project Detail
B13: Profile
C14: Table 1 | D14: Profile
B15: MIS
C16: Table 1 | D16: MIS
B17: Networth
C18: Table 1 | D18: Networth
B19: Completed
C20: Table 1 | D20: Completed
B21: Promoter Land bank
C22: Table 1 | D22: Promoter Land bank
B23: Ongoing
C24: Table 1 | D24: Ongoing
B25: Debt
C26: Table 1 | D26: Debt
B27: COP-MOF
C28: Table 1 | D28: COP-MOF
B29: Sheet1 - PivotTable1
C30: Table 1 | D30: Sheet1 - PivotTable1
B31: Sheet3 - PivotTable1
C32: Table 1 | D32: Sheet3 - PivotTable1
B33: Sheet3 - Table 1
C34: Table 1 | D34: Sheet3 - Table 1
B35: Sheet7 - PivotTable1
C36: Table 1 | D36: Sheet7 - PivotTable1
B37: Sheet8 - PivotTable2
C38: Table 1 | D38: Sheet8 - PivotTable2
B39: Sheet8 - Table 1
C40: Table 1 | D40: Sheet8 - Table 1
B41: Sheet9 - PivotTable2
C42: Table 1 | D42: Sheet9 - PivotTable2
B43: Sheet10 - PivotTable1
C44: PivotTable1 | D44: Sheet10 - PivotTable1 - PivotTa
C45: Table 1 | D45: Sheet10 - PivotTable1 - Table 1
B46: Sheet10 - Table 1
C47: Table 1 | D47: Sheet10 - Table 1
B48: Sheet12 - PivotTable2
C49: PivotTable2 | D49: Sheet12 - PivotTable2 - PivotTa
C50: Table 1 | D50: Sheet12 - PivotTable2 - Table 1
B51: Sheet13 - PivotTable3
C52: PivotTable3 | D52: Sheet13 - PivotTable3 - PivotTa
C53: Table 1 | D53: Sheet13 - PivotTable3 - Table 1
B54: Velocity
C55: Table 1 | D55: Velocity
B56: Sheet16
C57: Table 1 | D57: Sheet16
B58: Sheet11 - PivotTable1
C59: PivotTable1 | D59: Sheet11 - PivotTable1 - PivotTa
C60: Table 1 | D60: Sheet11 - PivotTable1 - Table 1
B61: Sold- Prime
C62: Table 1 | D62: Sold- Prime
B63: Unsold-Prime
C64: Table 1 | D64: Unsold-Prime
B65: Sheet14 - PivotTable1
C66: Table 1 | D66: Sheet14 - PivotTable1
B67: Sheet15 - PivotTable2
C68: Table 1 | D68: Sheet15 - PivotTable2
B69: Sheet15 - Table 1
C70: Table 1 | D70: Sheet15 - Table 1
B71: Unsold
C72: Table 1 | D72: Unsold
B73: Collection Velocity
C74: Table 1 | D74: Collection Velocity
B75: Sheet5
C76: Table 1 | D76: Sheet5
B77: Sheet4
C78: Table 1 | D78: Sheet4
B79: Sheet6
C80: Table 1 | D80: Sheet6
B81: COP & MOF
C82: Table 1 | D82: COP & MOF
B83: GST
C84: Table 1 | D84: GST

Sheet Project Detail
B1: PROJECT SPECIFIC ANALYSIS
A3: A | B3: Name of Developer: | C3: ABC Developer
B4: Date of Incorporation: | C4: 44929
B5: Registration number: | C5: REG12345
B6: PAN No: | C6: PAN123456
B7: Registered Address: | C7: Qube Software Park Bellandur
B8: Corporate Office | C8: SSG Office Domlur
B9: Project Name: | C9: Project 1
B10: Location Address : | C10: Address Bangalore
B11: Rera Registration No | C11: Rera1234567
B12: GST No | C12: GST1234567
B13: Project start Month / Year | C13: 45017
B14: Project End Month / Year | C14: 45261
B15: Google Link of Site | C15: www.google.com
B16: Paid Up Capital | C16: 10000
B17: Auditor Name and Address | C17: A K Sharma, Indiranagar
B18: Authorised Capital | C18: Capital
A20: B | B20: Land Details
B21: Land Area (sq. Mtr) | C21: 100 | D21: =C21/4047 -> 0.024709661
B22: Type of land | C22: Residentail
B23: Name of the landowner | C23: =C3 -> ABC Developer
B24: In case of Joint Venture (share in terms of built up area) | C24: Promoter 's share | D24: 1 | E24: Joint Venture Partner's Share | G24: ____%
B25: TDR (if any) | C25: N.A
A27: C | B27: Structure Specification
B28: Total Construction Area (sq ft)
B29: No. of Buildings | C29: 5
A31: D | B31: Sharing Ratio (in case of JV)
B32: Particulars | C32: Saleable are (sqft) | D32: No. of flats | E32: No. of shops
B34: Promoters Share
B35: Joint Venture Partner's Share
B37: Total | C37: =C35+C34 -> 0 | D37: =D35+D34 -> 0 | E37: =SUM(E34:E35) -> 0
A39: E | B39: Break up of units
B40: Particulars | C40: Apartments | D40: Other | E40: Total
B42: Construction Work Start date
B43: Expected Completion Date
B44: No. of Floors
B45: Flats
B46: No. of flats | E46: =C46+D46 -> 0
B47: Average Area per flat (sq ft)
B48: Saleable Area (sqft.) | C48: =C34 -> 0 | E48: =C48+D48 -> 0
B49: Shops/offices
B50: No. of shops / offices | E50: =C50+D50 -> 0
B51: Average Area per shop/office (sq ft)
B52: Saleable Area (sqft.) | E52: =C52+D52 -> 0
B53: Total No. of Units (Flats+shops+offices) | C53: =C46+C50 -> 0 | D53: =D46+D50 -> 0 | E53: =C53+D53 -> 0
B54: Total Saleable Area (sqft.) | C54: =C48+C52 -> 0 | D54: =D48+D52 -> 0 | E54: =C54+D54 -> 0

Sheet Profile
A1: INFORMATION MAMORANDUM | L1: Name of Person | M1: Qualification | N1: Functions | O1: Experience in Years
A3: ABOUTE-
B10: Date Of Birth
B11: DIN
B12: PAN
B13: AADHAR
B14: PASSPORT
B15: ADDRESS
B21: Date Of Birth
B22: DIN
B23: PAN
B24: AADHAR
B25: PASSPORT
B26: ADDRESS

Sheet MIS
A1: Sl No. | B1: Flat no | C1: Tower No | D1: Sold/Unsold | E1: Date of Booking | F1: Month | G1: Year | H1: Name of Customer | I1: Sealable Area (in sq ft) | J1: Agreement value | K1: Amount Received as on 28-02-2025 | L1: Amount Receivable | M1: Name of Financing Institution
A2: 1 | B2: G-1 | C2: A | D2: Unsold | I2: 1176.5052
A3: 2 | B3: G-2 | C3: A | D3: Unsold | I3: 1703.5106
A4: 3 | B4: A/101 | C4: A | D4: Sold | E4: 45418 | F4: may | G4: 2024 | H4: Satish Pukhraj Mutha | I4: 1187.59 | J4: 33809524 | K4: 10000000 | L4: =J4-K4 -> 23809524
A5: 4 | B5: A/102 | C5: A | D5: Unsold | I5: 1703.51
A6: 5 | B6: A/104 | C6: A | D6: Unsold | I6: 760.69
A7: 6 | B7: B/101 | C7: B | D7: Unsold | I7: 854.34
A8: 7 | B8: B/102 | C8: B | D8: Not for Sale | I8: 630.44748
A9: 8 | B9: B/103 | C9: B | D9: Not for Sale | I9: 620.65
A10: 9 | B10: B/104 | C10: B | D10: Not for Sale | I10: 802.34856
A11: 10 | B11: A/201 | C11: A | D11: Unsold | I11: 752.51
A12: 11 | B12: A/202 | C12: A | D12: Not for Sale | I12: 752.51124
A13: 12 | B13: A/203 | C13: A | D13: Not for Sale | I13: 752.51124
A14: 13 | B14: A/204 | C14: A | D14: Unsold | I14: 760.69
A15: 14 | B15: B/201 | C15: B | D15: Not for Sale | I15: 854.34
A16: 15 | B16: B/202 | C16: B | D16: Not for Sale | I16: 750.35844
... A26: 25 | B26: B/304 | C26: B | D26: Not for Sale | I26: 802.34856
A27: 26 | B27: A/401 | C27: A | D27: Unsold | E27: 45414 | F27: may | G27: 2024 | H27: Alfred Roy Rodrigues | I27: 752.51124 | J27: 22380952 | K27: =J27*10% -> 2238095.2 | L27: =J27-K27 -> 20142857
A28: 27 | B28: A/402 | C28: A | D28: Not for Sale | I28: 752.51124
A29: 28 | B29: A/403 | C29: A | D29: Not for Sale | I29: 752.51124
A30: 29 | B30: A/404 | C30: A | D30: Unsold | I30: 760.69
A31: 30 | B31: B/401 | C31: B | D31: Not for Sale | I31: 854.34
A32: 31 | B32: B/402 | C32: B | D32: Not for Sale | I32: 750.35844
A33: 32 | B33: B/403 | C33: B | D33: Not for Sale | I33: 750.35844
A34: 33 | B34: B/404 | C34: B | D34: Not for Sale | I34: 802.34856
A35: 34 | B35: A/501 | C35: A | D35: Unsold | E35: 45420 | F35: may | G35: 2024 | H35: Ruchita Mahendra Gala | I35: 752.51124 | J35: 23600000 | K35: =J35*10% -> 2360000 | L35: =J35-K35 -> 21240000
A36: 35 | B36: A/502 | C36: A | D36: Not for Sale | I36: 752.51124
A37: 36 | B37: A/503 | C37: A | D37: Not for Sale | I37: 752.51124
A38: 37 | B38: A/504 | C38: A | D38: Unsold | E38: 45420 | F38: may | G38: 2024 | H38: Meena Mahendra Gala | I38: 760.69 | J38: 23851429 | K38: =J38*10% -> 2385142.9 | L38: =J38-K38 -> 21466286
A39: 38 | B39: B/501 | C39: B | D39: Not for Sale | I39: 854.34
A40: 39 | B40: B/502 | C40: B | D40: Not for Sale | I40: 750.35844
A41: 40 | B41: B/503 | C41: B | D41: Not for Sale | I41: 750.35844
A42: 41 | B42: B/504 | C42: B | D42: Not for Sale | I42: 802.34856
A43: 42 | B43: A/601 | C43: A | D43: Unsold | I43: 752.51124
A44: 43 | B44: A/602 | C44: A | D44: Not for Sale | I44: 752.51124
A45: 44 | B45: A/603 | C45: A | D45: Unsold | I45: 752.51124
A46: 45 | B46: A/604 | C46: A | D46: Not for Sale | I46: 760.69
A47: 46 | B47: B/601 | C47: B | D47: Not for Sale | I47: 854.34
A48: 47 | B48: B/602 | C48: B | D48: Not for Sale | I48: 750.35844
A49: 48 | B49: B/603 | C49: B | D49: Unsold | I49: 750.35844
A50: 49 | B50: B/604 | C50: B | D50: Not for Sale | I50: 802.34856
... A55: 54 | B55: B/703 | C55: B | D55: Unsold | I55: 863.17
A56: 55 | B56: B/704 | C56: B | D56: Unsold | E56: 45426 | F56: may | G56: 2024 | H56: Anit Bharat Soni | I56: 902.13 | J56: 28314286 | K56: =J56*10% -> 2831428.6 | L56: =J56-K56 -> 25482857
A57: 56 | B57: A/801 | C57: A | D57: Unsold | I57: 752.51124
A58: 57 | B58: A/802 | C58: A | D58: Not for Sale | I58: 752.51124
A59: 58 | B59: A/803 | C59: A | D59: Not for Sale | I59: 752.51124
A60: 59 | B60: A/804 | C60: A | D60: Sold | E60: 45430 | F60: may | G60: 2024 | H60: Bhavesh G Kothari | I60: 760.69 | J60: 18200000 | K60: =J60*10% -> 1820000 | L60: =J60-K60 -> 16380000
A61: 60 | B61: B/801 | C61: B | D61: Not for Sale | I61: 958.1
A62: 61 | B62: B/802 | C62: B | D62: Unsold | I62: 750.35844
A63: 62 | B63: B/803 | C63: B | D63: Unsold | I63: 750.35844
A64: 63 | B64: B/804 | C64: B | D64: Unsold | E64: 45430 | F64: may | G64: 2024 | H64: Ganpat Lal Kothari | I64: 902.13 | J64: 28314286 | K64: =J64*10% -> 2831428.6 | L64: =J64-K64 -> 25482857
A65: 64 | B65: A/901 | C65: A | D65: Unsold | I65: 752.51124
A66: 65 | B66: A/902 | C66: A | D66: Not for Sale | I66: 752.51124
A67: 66 | B67: A/903 | C67: A | D67: Unsold | I67: 752.51124
A68: 67 | B68: A/904 | C68: A | D68: Unsold | I68: 760.69
A69: 68 | B69: B/901 | C69: B | D69: Unsold | I69: 958.1
A70: 69 | B70: B/902 | C70: B | D70: Unsold | E70: 45413 | F70: may | G70: 2024 | H70: Ajay Walia | I70: 750.35844 | J70: 18000000 | K70: =J70*10% -> 1800000 | L70: =J70-K70 -> 16200000
A71: 70 | B71: B/903 | C71: B | D71: Sold | E71: 45420 | F71: may | G71: 2024 | H71: Ashita Mahendra Gala | I71: 750.35844 | J71: 18000000 | K71: =J71*10% -> 1800000 | L71: =J71-K71 -> 16200000
A72: 71 | B72: B/904 | C72: B | D72: Unsold | I72: 902.13
A73: 72 | B73: A/1001 | C73: A | D73: Unsold | I73: 752.51124
A74: 73 | B74: A/1002 | C74: A | D74: Unsold | E74: 45420 | F74: may | G74: 2024 | H74: Miloni Mahendra Gala | I74: 752.51124 | J74: 18000000 | K74: =J74*10% -> 1800000 | L74: =J74-K74 -> 16200000
A75: 74 | B75: A/1003 | C75: A | D75: Sold | E75: 45414 | F75: may | G75: 2024 | H75: Sunil Grover | I75: 752.51124 | J75: 18000000 | K75: =J75*10% -> 1800000 | L75: =J75-K75 -> 16200000
A76: 75 | B76: A/1004 | C76: A | D76: Unsold | I76: 760.69
A77: 76 | B77: B/1001 | C77: B | D77: Sold | E77: 45414 | F77: may | G77: 2024 | H77: Seema Grover | I77: 958.1 | J77: 29500000 | K77: =J77*10% -> 2950000 | L77: =J77-K77 -> 26550000
A78: 77 | B78: B/1002 | C78: B | D78: Unsold | I78: 750.35844
A79: 78 | B79: B/1003 | C79: B | D79: Unsold | I79: 750.35844
A80: 79 | B80: B/1004 | C80: B | D80: Unsold | I80: 902.13
A81: 80 | B81: A/1101 | C81: A | D81: Unsold | I81: 752.51124
A82: 81 | B82: A/1102 | C82: A | D82: Unsold | I82: 752.51124
A83: 82 | B83: A/1103 | C83: A | D83: Unsold | E83: 45429 | F83: may | G83: 2024 | H83: Chandrakant N Bodiwala | I83: 752.51124 | J83: 18000000 | K83: =J83*10% -> 1800000 | L83: =J83-K83 -> 16200000
A84: 83 | B84: A/1104 | C84: A | D84: Unsold | I84: 760.69
A85: 84 | B85: B/1101 | C85: B | D85: Unsold | I85: 958.1
A86: 85 | B86: B/1102 | C86: B | D86: Unsold | I86: 750.35844
A87: 86 | B87: B/1103 | C87: B | D87: Unsold | E87: 45579 | F87: October | G87: 2024 | H87: Bharat Kumar jain | I87: 750.35844 | J87: 18000000 | K87: =J87*10% -> 1800000 | L87: =J87-K87 -> 16200000
A88: 87 | B88: B/1104 | C88: B | D88: Unsold | E88: 45405 | F88: October | G88: 2024 | H88: Mehul J Dekhtawala | I88: 902.13 | J88: 28314286 | K88: =J88*10% -> 2831428.6 | L88: =J88-K88 -> 25482857
A89: 88 | B89: A/1202 | C89: A | D89: Unsold | I89: 752.51124
A90: 89 | B90: A/1203 | C90: A | D90: Unsold | I90: 752.51124
A91: 90 | B91: A/1204 | C91: A | D91: Unsold | I91: 760.69
A92: 91 | B92: B/1201 | C92: B | D92: Unsold | I92: 958.1
A93: 92 | B93: B/1202 | C93: B | D93: Unsold | I93: 750.35844
A94: 93 | B94: B/1203 | C94: B | D94: Unsold | I94: 750.35844

Sheet Networth
A3: List of Directors | D3: DIN
A4: 1
A5: 2
A6: 3
A7: 4
A9: List of Shareholders | D9: %
A10: 1
A11: 2
A12: 3
A13: 4
C14: =SUM(C10:C13) -> 0 | D14: =SUM(D10:D13) -> 0

Sheet Completed
B2: S .No. | C2: Project Name | D2: Location | E2: Total Area | F2: Sold Area | G2: Area Unsold | H2: Sold Value | I2: Unsold Value | J2: Year of completion | K2: Leased area (sq.ft.)
E3: sq. ft. | F3: sq. ft. | G3: sq. ft. | H3: Rs. Crs. | I3: Rs. Crs.
B4: 1
C5: Total | E5: =SUM(E4:E4) -> 0 | F5: =SUM(F4:F4) -> 0 | G5: =SUM(G4:G4) -> 0 | H5: =SUM(H4:H4) -> 0 | I5: =SUM(I4:I4) -> 0

Sheet Promoter Land bank
A2: S.no. | B2: Property address | C2: Property owner | D2: Property area | E2: Property Market value | F2: Date of acquisition

Sheet Ongoing
B3: Sr. No. | C3: Project Name | D3: Company/Firm Name | E3: Location | F3: Start | G3: End | H3: Const. Stage | I3: Land Area (Acre) | J3: Total | K3: Sold | L3: Unsold | M3: Total Cost | N3: Incurred | O3: Balance | P3: Sold Value | Q3: Received | R3: Receivable | S3: Unsold | T3: Total Receivables | U3: Net Surplus
B4: 1
B5: 2
J6: =SUM(J4:J5) -> 0 | K6: =SUM(K4:K5) -> 0 | L6: =SUM(L4:L5) -> 0 | M6: =SUM(M4:M5) -> 0 | N6: =SUM(N4:N5) -> 0 | O6: =SUM(O4:O5) -> 0 | P6: =SUM(P4:P5) -> 0 | Q6: =SUM(Q4:Q5) -> 0 | ... U6: =SUM(U4:U5) -> 0

Sheet Debt
A1: S.No. | B1: Name of the Bank/FI | C1: Borrower firm/company | D1: Tenure (months) | E1: Sanctioned (Cr.) | F1: Disb. (Cr.) | G1: Balance (Cr.) | H1: Project name
A2: 1
A3: 2
E4: =SUM(E2:E3) -> 0 | F4: =SUM(F2:F3) -> 0 | G4: =SUM(G2:G3) -> 0

Sheet COP-MOF
A1: Project - COMOF
A2: AS ON 28-02-2025
A3: PARTICULARS | B3: Total Cost | C3: Incurred | D3: To be incurred
A4: Land Cost (stamp duty) | B4: 2 | C4: 2 | D4: =B4-C4 -> 0
A5: EDC | D5: =B5-C5 -> 0
A6: IDC | D6: =B6-C6 -> 0
A7: License fee | D7: =B7-C7 -> 0
A8: Other Statutory Fee | B8: 35 | C8: 25 | D8: =B8-C8 -> 10
A9: Construction cost | B9: 43 | C9: 5 | D9: =B9-C9 -> 38
A10: Sales and Marketing Cost | B10: 5 | C10: 0.25 | D10: =B10-C10 -> 4.75
A11: Finance Cost | B11: 10 | C11: 0.5 | D11: =B11-C11 -> 9.5
A12: Total (A) | B12: =SUM(B4:B11) -> 95 | C12: =SUM(C4:C11) -> 32.75 | D12: =SUM(D4:D11) -> 62.25
A14: Means of Finance
A15: Customer Advance | B15: 35 | C15: 2 | D15: =B15-C15 -> 33
A16: Promoter Funds | B16: 25 | C16: 23 | D16: =B16-C16 -> 2
A17: Bank Funds | B17: 35 | C17: 8 | D17: =B17-C17 -> 27
A18: MEANS OF FINANCE | B18: =SUM(B15:B17) -> 95 | C18: =SUM(C15:C17) -> 33 | D18: =SUM(D15:D17) -> 62

Sheet Sheet1 - PivotTable1
A1: PivotTable1
A2: Date of booking (Year) | B2: Date of booking (Qtr) | C2: Date of booking (Month) | D2: Saleable Area in sq ft (Sum) | E2: Recd (Sum) | F2: Total Sale Price (Sum) | G2: Unit No (Count All)
A3: 41640 | B3: 44013 | C3: 44013 | D3: 17587 | E3: 53408445 | F3: 55031325 | G3: 13
C4: 44044 | D4: 8423 | E4: 27050551 | F4: 27409625 | G4: 7
C5: 44075 | D5: 12343 | E5: 39783228 | F5: 40492334 | G5: 9
B6: 44013 | D6: 38353 | E6: 120242224 | F6: 122933284 | G6: 29
B7: 44105 | C7: 44105 | D7: 20302 | E7: 64356642 | F7: 66933653 | G7: 16
C8: 44136 | D8: 13585 | E8: 45289300 | F8: 46498575 | G8: 10
C9: 44166 | D9: 14176 | E9: 46303393 | F9: 47775627 | G9: 10
B10: 44105 | D10: 48063 | E10: 155949335 | F10: 161207855 | G10: 36
A11: 41640 | D11: 86416 | E11: 276191559 | F11: 284141139 | G11: 65
A12: 42005 | B12: 43831 | C12: 43831 | D12: 13121 | E12: 42108347 | F12: 43887914 | G12: 10
C13: 43862 | D13: 14744 | E13: 48723175 | F13: 50484142 | G13: 11
C14: 43891 | D14: 7877 | E14: 25792324 | F14: 26422396 | G14: 6
B15: 43831 | D15: 35742 | E15: 116623846 | F15: 120794452 | G15: 27
B16: 43922 | C16: 43922 | D16: 3411 | E16: 10450217 | F16: 11106460 | G16: 3
C17: 43952 | D17: 6349 | E17: 21774749 | F17: 22747874 | G17: 4
C18: 43983 | D18: 10615 | E18: 34698573 | F18: 35793047 | G18: 8
B19: 43922 | D19: 20375 | E19: 66923539 | F19: 69647381 | G19: 15
B20: 44013 | C20: 44013 | D20: 7750 | E20: 27827250 | F20: 28454676 | G20: 6
C21: 44044 | D21: 1137 | E21: 3803125 | F21: 3966695 | G21: 1
C22: 44075 | D22: 4107 | E22: 13296569 | F22: 14645770 | G22: 3
B23: 44013 | D23: 12994 | E23: 44926944 | F23: 47067141 | G23: 10
B24: 44105 | C24: 44105 | D24: 2865 | E24: 7307471 | F24: 7549405 | G24: 2
C25: 44136 | D25: 2115 | E25: 4974479 | F25: 5271080 | G25: 1
C26: 44166 | D26: 25138 | E26: 52008485 | F26: 53404695 | G26: 17
B27: 44105 | D27: 30118 | E27: 64290435 | F27: 66225180 | G27: 20
A28: 42005 | D28: 99229 | E28: 292764764 | F28: 303734154 | G28: 72
A29: 42370 | B29: 43831 | C29: 43831 | D29: 9930 | E29: 25694632 | F29: 28734621 | G29: 6
C30: 43862 | D30: 3456 | E30: 9832081 | F30: 10315940 | G30: 2
C31: 43891 | D31: 4853 | E31: 11631998 | F31: 12757021 | G31: 3
B32: 43831 | D32: 18239 | E32: 47158711 | F32: 51807582 | G32: 11
B33: 43922 | C33: 43922 | D33: 3875 | E33: 13406346 | F33: 13824630 | G33: 3
C34: 43952 | D34: 6972 | E34: 22409091 | F34: 24048392 | G34: 5
C35: 43983 | D35: 3643 | E35: 11606019 | F35: 12494616 | G35: 3
B36: 43922 | D36: 14490 | E36: 47421456 | F36: 50367638 | G36: 11
B37: 44013 | C37: 44013 | D37: 9319 | E37: 31407232 | F37: 34676605 | G37: 6
C38: 44044 | D38: 4107 | E38: 13753659 | F38: 14948479 | G38: 3
C39: 44075 | D39: 5012 | E39: 16859698 | F39: 17023268 | G39: 4
B40: 44013 | D40: 18438 | E40: 62020589 | F40: 66648352 | G40: 13
B41: 44105 | C41: 44105 | D41: 19554 | E41: 63428590 | F41: 64801809 | G41: 12
C42: 44136 | D42: 7970 | E42: 23024376 | F42: 23551945 | G42: 5
B43: 44105 | D43: 27524 | E43: 86452966 | F43: 88353754 | G43: 17
A44: 42370 | D44: 78691 | E44: 243053722 | F44: 257177326 | G44: 52
A45: 42736 | B45: 43831 | C45: 43831 | D45: 1369 | E45: 5243266 | F45: 5243270 | G45: 1
C46: 43862 | D46: 13293 | E46: 47517013 | F46: 48406371 | G46: 9
C47: 43891 | D47: 16981 | E47: 58911827 | F47: 60039818 | G47: 11
B48: 43831 | D48: 31643 | E48: 111672106 | F48: 113689459 | G48: 21
B49: 43922 | C49: 43922 | D49: 13106 | E49: 39527491 | F49: 39945770 | G49: 8
C50: 43952 | D50: 15999 | E50: 56946613 | F50: 58129958 | G50: 10
C51: 43983 | D51: 24581 | E51: 88656177 | F51: 89973944 | G51: 18
B52: 43922 | D52: 53686 | E52: 185130281 | F52: 188049672 | G52: 36
B53: 44013 | C53: 44013 | D53: 16964 | E53: 55730668 | F53: 56385119 | G53: 12
C54: 44044 | D54: 31972 | E54: 107527095 | F54: 108903601 | G54: 24
C55: 44075 | D55: 16870 | E55: 58912788 | F55: 60448203 | G55: 10
B56: 44013 | D56: 65806 | E56: 222170551 | F56: 225736923 | G56: 46
B57: 44105 | C57: 44105 | D57: 14258 | E57: 48734669 | F57: 49107378 | G57: 11
C58: 44136 | D58: 11234 | E58: 37174537 | F58: 37386057 | G58: 8
C59: 44166 | D59: 17444 | E59: 61855465 | F59: 62710661 | G59: 11
B60: 44105 | D60: 42936 | E60: 147764671 | F60: 149204096 | G60: 30
A61: 42736 | D61: 194071 | E61: 666737609 | F61: 676680150 | G61: 133
A62: 43101 | B62: 43831 | C62: 43831 | D62: 11174 | E62: 39944057 | F62: 40107651 | G62: 7
C63: 43862 | D63: 16682 | E63: 59792678 | F63: 60375180 | G63: 12
C64: 43891 | D64: 23378 | E64: 81500601 | F64: 83111637 | G64: 15
B65: 43831 | D65: 51234 | E65: 181237336 | F65: 183594468 | G65: 34
B66: 43922 | C66: 43922 | D66: 28500 | E66: 101851348 | F66: 102579364 | G66: 17
C67: 43952 | D67: 24636 | E67: 82629716 | F67: 83333091 | G67: 15
C68: 43983 | D68: 27462 | E68: 96894518 | F68: 97475884 | G68: 19
B69: 43922 | D69: 80598 | E69: 281375582 | F69: 283388339 | G69: 51
B70: 44013 | C70: 44013 | D70: 32723 | E70: 106030483 | F70: 107453740 | G70: 22
C71: 44044 | D71: 12750 | E71: 44682594 | F71: 44899200 | G71: 9
C72: 44075 | D72: 17866 | E72: 60125152 | F72: 61377399 | G72: 10
B73: 44013 | D73: 63339 | E73: 210838229 | F73: 213730339 | G73: 41
B74: 44105 | C74: 44105 | D74: 16059 | E74: 57353184 | F74: 57771464 | G74: 11
C75: 44136 | D75: 3875 | E75: 14178705 | F75: 14178705 | G75: 3
C76: 44166 | D76: 15999 | E76: 58989940 | F76: 59693510 | G76: 10
B77: 44105 | D77: 35933 | E77: 130521829 | F77: 131643679 | G77: 24
A78: 43101 | D78: 231104 | E78: 803972976 | F78: 812356825 | G78: 150
A79: 43466 | B79: 43831 | C79: 43831 | D79: 25312 | E79: 92945956 | F79: 94342422 | G79: 16
C80: 43862 | D80: 15628 | E80: 53286309 | F80: 53749749 | G80: 9
C81: 43891 | D81: 27699 | E81: 95990939 | F81: 98530861 | G81: 16
B82: 43831 | D82: 68639 | E82: 242223204 | F82: 246623032 | G82: 41
B83: 43922 | C83: 43922 | D83: 6601 | E83: 24900000 | F83: 25141930 | G83: 4
C84: 43952 | D84: 18132 | E84: 65110536 | F84: 65110536 | G84: 11
C85: 43983 | D85: 7579 | E85: 26800440 | F85: 26800440 | G85: 4
B86: 43922 | D86: 32312 | E86: 116810976 | F86: 117052906 | G86: 19
B87: 44013 | C87: 44013 | D87: 20032 | E87: 68759742 | F87: 70060772 | G87: 11
C88: 44044 | D88: 9837 | E88: 37862230 | F88: 37862230 | G88: 7
C89: 44075 | D89: 19458 | E89: 72761787 | F89: 72861380 | G89: 13
B90: 44013 | D90: 49327 | E90: 179383759 | F90: 180784382 | G90: 31
B91: 44105 | C91: 44105 | D91: 37282 | E91: 131644281 | F91: 133149780 | G91: 24
C92: 44136 | D92: 16565 | E92: 63134311 | F92: 63134311 | G92: 11
C93: 44166 | D93: 8236 | E93: 27687620 | F93: 27929550 | G93: 6
B94: 44105 | D94: 62083 | E94: 222466212 | F94: 224213641 | G94: 41
A95: 43466 | D95: 212361 | E95: 760884151 | F95: 768673961 | G95: 132
A96: 43831 | B96: 43831 | C96: 43831 | D96: 19537 | E96: 65869704 | F96: 66196844 | G96: 11
C97: 43862 | D97: 6833 | E97: 26241800 | F97: 26241800 | G97: 4
C98: 43891 | D98: 7424 | E98: 25503150 | F98: 25503150 | G98: 4
B99: 43831 | D99: 33794 | E99: 117614654 | F99: 117941794 | G99: 19
B100: 43922 | C100: 43922 | D100: 2599 | E100: 10270030 | F100: 10270030 | G100: 1
...

Sheet Sheet3 - PivotTable1
A1: PivotTable1
A2: Allotment Date (Year) | B2: Allotment Date (Qtr) | C2: Allotment Date (Month) | D2: Unit No. (Count All) | E2: Area (Sum) | F2: Received (Sum) | G2: Unit Cost (Sum)
A3: 40909 | B3: 44105 | C3: 44105 | D3: 4 | E3: 1786.92 | F3: 9904352 | G3: 9904358
C4: 44136 | D4: 13 | E4: 6810.02 | F4: 31006810 | G4: 31006797
C5: 44166 | D5: 12 | E5: 6898.82 | F5: 23696037 | G5: 23695063
B6: 44105 | D6: 29 | E6: 15495.76 | F6: 64607199 | G6: 64606218
A7: 40909 | D7: 29 | E7: 15495.76 | F7: 64607199 | G7: 64606218
A8: 41275 | B8: 43831 | C8: 43831 | D8: 33 | E8: 15776.88 | F8: 79653499 | G8: 79879943
C9: 43862 | D9: 18 | E9: 10892.1 | F9: 39708573 | G9: 40732635
C10: 43891 | D10: 19 | E10: 9788.42 | F10: 45968937 | G10: 45978132
B11: 43831 | D11: 70 | E11: 36457.4 | F11: 165331009 | G11: 166590710
B12: 43922 | C12: 43922 | D12: 28 | E12: 15118.04 | F12: 63738421 | G12: 63740323
C13: 43952 | D13: 14 | E13: 7820.53 | F13: 33586917 | G13: 33599760
C14: 43983 | D14: 11 | E14: 6717.85 | F14: 19741582 | G14: 19741259
B15: 43922 | D15: 53 | E15: 29656.42 | F15: 117066920 | G15: 117081342
B16: 44013 | C16: 44013 | D16: 13 | E16: 7311.42 | F16: 37605172 | G16: 37617861
C17: 44044 | D17: 14 | E17: 7329.01 | F17: 31938383 | G17: 32065135
C18: 44075 | D18: 23 | E18: 13965.77 | F18: 56774309 | G18: 56854566
B19: 44013 | D19: 50 | E19: 28606.2 | F19: 126317864 | G19: 126537562
B20: 44105 | C20: 44105 | D20: 17 | E20: 8644.15 | F20: 42874189 | G20: 43102446
C21: 44136 | D21: 15 | E21: 7258.13 | F21: 41811793 | G21: 41991904
C22: 44166 | D22: 11 | E22: 5471.21 | F22: 25445608 | G22: 25444977
B23: 44105 | D23: 43 | E23: 21373.49 | F23: 110131590 | G23: 110539327
A24: 41275 | D24: 216 | E24: 116093.51 | F24: 518847383 | G24: 520748941
A25: 41640 | B25: 43831 | C25: 43831 | D25: 21 | E25: 10023.34 | F25: 53394300 | G25: 53561816
C26: 43862 | D26: 11 | E26: 4341.89 | F26: 17208806 | G26: 17345988
C27: 43891 | D27: 14 | E27: 5875.78 | F27: 29126932 | G27: 29159221
B28: 43831 | D28: 46 | E28: 20241.01 | F28: 99730038 | G28: 100067025
B29: 43922 | C29: 43922 | D29: 7 | E29: 2978.2 | F29: 16379741 | G29: 16378947
C30: 43952 | D30: 20 | E30: 9323.83 | F30: 44887670 | G30: 44941182
C31: 43983 | D31: 5 | E31: 2084.74 | F31: 12417368 | G31: 12418125
B32: 43922 | D32: 32 | E32: 14386.77 | F32: 73684779 | G32: 73738254
B33: 44013 | C33: 44013 | D33: 6 | E33: 2096.49 | F33: 13654827 | G33: 13649381
C34: 44044 | D34: 2 | E34: 1377.6 | F34: 5787994 | G34: 5787994
C35: 44075 | D35: 12 | E35: 5442.3 | F35: 28750882 | G35: 28750885
B36: 44013 | D36: 20 | E36: 8916.39 | F36: 48193703 | G36: 48188260
B37: 44105 | C37: 44105 | D37: 14 | E37: 7317.3 | F37: 40684234 | G37: 40684237
C38: 44136 | D38: 12 | E38: 5752.53 | F38: 38585983 | G38: 38739565
C39: 44166 | D39: 4 | E39: 2613.67 | F39: 9744954 | G39: 10238266
B40: 44105 | D40: 30 | E40: 15683.5 | F40: 89015171 | G40: 89662068
A41: 41640 | D41: 128 | E41: 59227.67 | F41: 310623691 | G41: 311655607
A42: 42005 | B42: 43831 | C42: 43831 | D42: 8 | E42: 4756.41 | F42: 25144572 | G42: 25159847
C43: 43862 | D43: 7 | E43: 3671.81 | F43: 16046718 | G43: 16069597
C44: 43891 | D44: 5 | E44: 2289.73 | F44: 12225706 | G44: 12398603
B45: 43831 | D45: 20 | E45: 10717.95 | F45: 53416996 | G45: 53628047
B46: 43922 | C46: 43922 | D46: 3 | E46: 2284.97 | F46: 9617823 | G46: 9617740
C47: 43952 | D47: 4 | E47: 1816.22 | F47: 8249282 | G47: 8393014
C48: 43983 | D48: 7 | E48: 3215.01 | F48: 12270369 | G48: 12587113
B49: 43922 | D49: 14 | E49: 7316.2 | F49: 30137474 | G49: 30597867
B50: 44013 | C50: 44013 | D50: 4 | E50: 1667.31 | F50: 10380547 | G50: 10407136
C51: 44044 | D51: 12 | E51: 6553.36 | F51: 35771248 | G51: 36264120
C52: 44075 | D52: 9 | E52: 5048.19 | F52: 23711385 | G52: 23781709
B53: 44013 | D53: 25 | E53: 13268.86 | F53: 69863180 | G53: 70452965
B54: 44105 | C54: 44105 | D54: 7 | E54: 2887.89 | F54: 15642133 | G54: 15665200
C55: 44136 | D55: 12 | E55: 6269.79 | F55: 31164805 | G55: 32035152
C56: 44166 | D56: 16 | E56: 7765.24 | F56: 44664083 | G56: 45891997
B57: 44105 | D57: 35 | E57: 16922.92 | F57: 91471021 | G57: 93592349
A58: 42005 | D58: 94 | E58: 48225.93 | F58: 244888671 | G58: 248271228
A59: 42370 | B59: 43831 | C59: 43831 | D59: 10 | E59: 5486.91 | F59: 28242423 | G59: 28381251
C60: 43862 | D60: 3 | E60: 2119.76 | F60: 10774912 | G60: 10774912
C61: 43891 | D61: 8 | E61: 3883.55 | F61: 24317152 | G61: 24329824
B62: 43831 | D62: 21 | E62: 11490.22 | F62: 63334487 | G62: 63485987
B63: 43922 | C63: 43922 | D63: 13 | E63: 6069.96 | F63: 29717638 | G63: 33134779
C64: 43952 | D64: 18 | E64: 7024.43 | F64: 22349572 | G64: 22423383
C65: 43983 | D65: 8 | E65: 3109.7 | F65: 18689307 | G65: 19425466
B66: 43922 | D66: 39 | E66: 16204.09 | F66: 70756517 | G66: 74983628
B67: 44013 | C67: 44013 | D67: 14 | E67: 7405.2 | F67: 39250328 | G67: 40999017
C68: 44044 | D68: 9 | E68: 4386.82 | F68: 21508441 | G68: 22669190
C69: 44075 | D69: 3 | E69: 1384.14 | F69: 6801369 | G69: 6962852
B70: 44013 | D70: 26 | E70: 13176.16 | F70: 67560138 | G70: 70631059
B71: 44105 | C71: 44105 | D71: 8 | E71: 3450.59 | F71: 14156276 | G71: 14310899
C72: 44136 | D72: 28 | E72: 14581.17 | F72: 39121038 | G72: 40105379
C73: 44166 | D73: 28 | E73: 14702.5 | F73: 41171706 | G73: 41854239
B74: 44105 | D74: 64 | E74: 32734.26 | F74: 94449020 | G74: 96270517
A75: 42370 | D75: 150 | E75: 73604.73 | F75: 296100162 | G75: 305371191
A76: 42736 | B76: 43831 | C76: 43831 | D76: 4 | E76: 2808.11 | F76: 8576988 | G76: 8576984
C77: 43862 | D77: 11 | E77: 7397.92 | F77: 46757772 | G77: 46665804
C78: 43891 | D78: 16 | E78: 7991.71 | F78: 35843957 | G78: 35843957
B79: 43831 | D79: 31 | E79: 18197.74 | F79: 91178717 | G79: 91086745
B80: 43922 | C80: 43922 | D80: 10 | E80: 5041.76 | F80: 21254645 | G80: 22523023
C81: 43952 | D81: 17 | E81: 8667.4 | F81: 36896595 | G81: 38213376
C82: 43983 | D82: 10 | E82: 6226.59 | F82: 19376123 | G82: 24740755
B83: 43922 | D83: 37 | E83: 19935.75 | F83: 77527363 | G83: 85477154
B84: 44013 | C84: 44013 | D84: 8 | E84: 3330.36 | F84: 20248438 | G84: 20830538
C85: 44044 | D85: 1 | E85: 297.82 | F85: 2063033 | G85: 2063714
C86: 44075 | D86: 7 | E86: 5856.07 | F86: 18220498 | G86: 18226886
B87: 44013 | D87: 16 | E87: 9484.25 | F87: 40531969 | G87: 41121138
B88: 44105 | C88: 44105 | D88: 15 | E88: 6930.48 | F88: 46761339 | G88: 47606544
C89: 44136 | D89: 10 | E89: 5139.92 | F89: 37999723 | G89: 37999724
C90: 44166 | D90: 6 | E90: 3187.33 | F90: 13653493 | G90: 15055138
B91: 44105 | D91: 31 | E91: 15257.73 | F91: 98414555 | G91: 100661406
A92: 42736 | D92: 115 | E92: 62875.47 | F92: 307652604 | G92: 318346443
A93: 43101 | B93: 43831 | C93: 43831 | D93: 9 | E93: 4193.96 | F93: 18924008 | G93: 18872916
C94: 43862 | D94: 2 | E94: 1159.22 | F94: 5650051 | G94: 5650052
C95: 43891 | D95: 3 | E95: 893.46 | F95: 3952634 | G95: 4422851
B96: 43831 | D96: 14 | E96: 6246.64 | F96: 28526693 | G96: 28945819
B97: 43922 | C97: 43922 | D97: 3 | E97: 1810.04 | F97: 13658837 | G97: 20189168
C98: 43952 | D98: 1 | E98: 446.73 | F98: 3456082 | G98: 3456082
C99: 43983 | D99: 2 | E99: 744.55 | F99: 5001259 | G99: 5001259
B100: 43922 | D100: 6 | E100: 3001.32 | F100: 22116178 | G100: 28646509
...

Sheet Sheet3 - Table 1
G4: =GETPIVOTDATA("Unit Cost",'Sheet3 - Table 1'!$A$2,"Years",2012)/10000000 -> #REF! | H4: =GETPIVOTDATA("Received",'Sheet3 - Table 1'!$A$2,"Years",2012)/10000000 -> #REF!
G5: =GETPIVOTDATA("Unit Cost",'Sheet3 - Table 1'!$A$2,"Years",2013)/10000000 -> #REF! | H5: =GETPIVOTDATA("Received",'Sheet3 - Table 1'!$A$2,"Years",2013)/10000000 -> #REF!
G6: =GETPIVOTDATA("Unit Cost",'Sheet3 - Table 1'!$A$2,"Years",2014)/10000000 -> #REF! | H6: =GETPIVOTDATA("Received",'Sheet3 - Table 1'!$A$2,"Years",2014)/10000000 -> #REF!
G7: =GETPIVOTDATA("Unit Cost",'Sheet3 - Table 1'!$A$2,"Years",2015)/10000000 -> #REF! | H7: =GETPIVOTDATA("Received",'Sheet3 - Table 1'!$A$2,"Years",2015)/10000000 -> #REF!
G8: =GETPIVOTDATA("Unit Cost",'Sheet3 - Table 1'!$A$2,"Years",2016)/10000000 -> #REF! | H8: =GETPIVOTDATA("Received",'Sheet3 - Table 1'!$A$2,"Years",2016)/10000000 -> #REF!
G9: =GETPIVOTDATA("Unit Cost",'Sheet3 - Table 1'!$A$2,"Years",2017)/10000000 -> #REF! | H9: =GETPIVOTDATA("Received",'Sheet3 - Table 1'!$A$2,"Years",2017)/10000000 -> #REF!
G10: =GETPIVOTDATA("Unit Cost",'Sheet3 - Table 1'!$A$2,"Years",2018)/10000000 -> #REF! | H10: =GETPIVOTDATA("Received",'Sheet3 - Table 1'!$A$2,"Years",2018)/10000000 -> #REF!
G11: =GETPIVOTDATA("Unit Cost",'Sheet3 - Table 1'!$A$2,"Years",2019)/10000000 -> #REF! | H11: =GETPIVOTDATA("Received",'Sheet3 - Table 1'!$A$2,"Years",2019)/10000000 -> #REF!
G12: =GETPIVOTDATA("Unit Cost",'Sheet3 - Table 1'!$A$2,"Years",2020)/10000000 -> #REF! | H12: =GETPIVOTDATA("Received",'Sheet3 - Table 1'!$A$2,"Years",2020)/10000000 -> #REF!
G13: =GETPIVOTDATA("Unit Cost",'Sheet3 - Table 1'!$A$2,"Years",2021)/10000000 -> #REF! | H13: =GETPIVOTDATA("Received",'Sheet3 - Table 1'!$A$2,"Years",2021)/10000000 -> #REF!

Sheet Sheet7 - PivotTable1
A1: PivotTable1
A2: Date of Booking (Year) | B2: Date of Booking (Qtr) | C2: Date of Booking (Month) | D2: Sold/ Unsold (Count All) | E2: Balance Amount (Sum) | F2: Amount Received (Sum) | G2: Total vlue of Flat (Sum) | H2: Saleable Area (Sum)
A3: 42005 | B3: 44013 | C3: 44044 | D3: 1 | E3: 14304500 | F3: 1460000 | G3: 15764500 | H3: 3845
B4: 44013 | D4: 1 | E4: 14304500 | F4: 1460000 | G4: 15764500 | H4: 3845
B5: 44105 | C5: 44105 | D5: 1 | E5: 2666414 | F5: 1922826 | G5: 4589240 | H5: 620
C6: 44166 | D6: 7 | E6: 4290078 | F6: 23132332 | G6: 27422410 | H6: 3905
B7: 44105 | D7: 8 | E7: 6956492 | F7: 25055158 | G7: 32011650 | H7: 4525
A8: 42005 | D8: 9 | E8: 21260992 | F8: 26515158 | G8: 47776150 | H8: 8370
A9: 42370 | B9: 43831 | C9: 43831 | D9: 6 | E9: 8753944.3 | F9: 14264256 | G9: 23018200 | H9: 3500
C10: 43862 | D10: 6 | E10: 4446697.4 | F10: 18932728 | G10: 23379425 | H10: 4255
C11: 43891 | D11: 14 | E11: 33410083 | F11: 60810392 | G11: 94220475 | H11: 21820
B12: 43831 | D12: 26 | E12: 46610725 | F12: 94007375 | G12: 140618100 | H12: 29575
B13: 43922 | C13: 43922 | D13: 12 | E13: 15856280 | F13: 25828470 | G13: 41684750 | H13: 6170
C14: 43952 | D14: 3 | E14: 5525419 | F14: 6849581 | G14: 12375000 | H14: 2460
C15: 43983 | D15: 12 | E15: 19617185 | F15: 47617495 | G15: 67234680 | H15: 12280
B16: 43922 | D16: 27 | E16: 40998884 | F16: 80295546 | G16: 121294430 | H16: 20910
B17: 44013 | C17: 44013 | D17: 5 | E17: 5548973.4 | F17: 9090506.6 | G17: 14639480 | H17: 2600
C18: 44044 | D18: 5 | E18: 4548929.9 | F18: 16245170 | G18: 20794100 | H18: 4280
C19: 44075 | D19: 2 | E19: 2973316.9 | F19: 6705683.1 | G19: 9679000 | H19: 1350
B20: 44013 | D20: 12 | E20: 13071220 | F20: 32041360 | G20: 45112580 | H20: 8230
B21: 44105 | C21: 44105 | D21: 13 | E21: 20120650 | F21: 29855030 | G21: 49975680 | H21: 7530
C22: 44136 | D22: 9 | E22: 24487810 | F22: 24449106 | G22: 48936915 | H22: 8800
C23: 44166 | D23: 5 | E23: 10025433 | F23: 12343167 | G23: 22368600 | H23: 4205
B24: 44105 | D24: 27 | E24: 54633893 | F24: 66647302 | G24: 121281195 | H24: 20535
A25: 42370 | D25: 92 | E25: 1.5531472e+08 | F25: 2.7299158e+08 | G25: 428306305 | H25: 79250
A26: 42736 | B26: 43831 | C26: 43831 | D26: 1 | E26: -148829.11 | F26: 3456579.1 | G26: 3307750 | H26: 655
C27: 43862 | D27: 1 | E27: 3503956.6 | F27: 5956043.4 | G27: 9460000 | H27: 2150
C28: 43891 | D28: 4 | E28: 9473371.9 | F28: 6961108.1 | G28: 16434480 | H28: 3060
B29: 43831 | D29: 6 | E29: 12828499 | F29: 16373731 | G29: 29202230 | H29: 5865
B30: 43922 | C30: 43922 | D30: 4 | E30: 3493133.7 | F30: 6280366.3 | G30: 9773500 | H30: 1795
C31: 43952 | D31: 8 | E31: 17264104 | F31: 18307871 | G31: 35571975 | H31: 5755
C32: 43983 | D32: 8 | E32: 18329567 | F32: 38155763 | G32: 56485330 | H32: 7725
B33: 43922 | D33: 20 | E33: 39086805 | F33: 62744000 | G33: 101830805 | H33: 15275
B34: 44013 | C34: 44013 | D34: 2 | E34: 1182630.3 | F34: 4021369.7 | G34: 5204000 | H34: 1160
C35: 44044 | D35: 4 | E35: 3307949.6 | F35: 7173925.4 | G35: 10481875 | H35: 1825
C36: 44075 | D36: 3 | E36: 3589276.8 | F36: 21303123 | G36: 24892400 | H36: 3360
B37: 44013 | D37: 9 | E37: 8079856.7 | F37: 32498418 | G37: 40578275 | H37: 6345
B38: 44105 | C38: 44105 | D38: 2 | E38: 5905328.3 | F38: 3519671.7 | G38: 9425000 | H38: 1350
C39: 44136 | D39: 4 | E39: 6449388.4 | F39: 11115262 | G39: 17564650 | H39: 3230
C40: 44166 | D40: 7 | E40: 7475406.2 | F40: 31212594 | G40: 38688000 | H40: 5915
B41: 44105 | D41: 13 | E41: 19830123 | F41: 45847527 | G41: 65677650 | H41: 10495
A42: 42736 | D42: 48 | E42: 79825284 | F42: 1.5746368e+08 | G42: 237288960 | H42: 37980
A43: 43101 | B43: 43831 | C43: 43831 | D43: 5 | E43: 14804769 | F43: 21107061 | G43: 35911830 | H43: 4785
C44: 43862 | D44: 2 | E44: 4142408.4 | F44: 5645691.6 | G44: 9788100 | H44: 1470
C45: 43891 | D45: 1 | E45: 60000 | F45: 1850000 | G45: 1910000 | H45: 200
B46: 43831 | D46: 8 | E46: 19007178 | F46: 28602752 | G46: 47609930 | H46: 6455
B47: 43922 | C47: 43922 | D47: 2 | E47: 503976.79 | F47: 2664023.2 | G47: 3168000 | H47: 720
C48: 43952 | D48: 6 | E48: 2348252.9 | F48: 13880907 | G48: 16229160 | H48: 3465
C49: 43983 | D49: 7 | E49: 15024116 | F49: 11769420 | G49: 26793535 | H49: 5440
B50: 43922 | D50: 15 | E50: 17876345 | F50: 28314350 | G50: 46190695 | H50: 9625
B51: 44013 | C51: 44013 | D51: 2 | E51: 1158402.9 | F51: 5011607.1 | G51: 6170010 | H51: 1335
C52: 44044 | D52: 4 | E52: 9999408.8 | F52: 6453331.2 | G52: 16452740 | H52: 2820
C53: 44075 | D53: 4 | E53: 7943749.7 | F53: 8053450.3 | G53: 15997200 | H53: 3535
B54: 44013 | D54: 10 | E54: 19101561 | F54: 19518389 | G54: 38619950 | H54: 7690
B55: 44105 | C55: 44105 | D55: 3 | E55: 1254000 | F55: 5050000 | G55: 6304000 | H55: 1385
C56: 44136 | D56: 3 | E56: 1691182.9 | F56: 6104107.1 | G56: 7795290 | H56: 1490
C57: 44166 | D57: 2 | E57: 1264952.7 | F57: 3438047.3 | G57: 4703000 | H57: 940
B58: 44105 | D58: 8 | E58: 4210135.5 | F58: 14592154 | G58: 18802290 | H58: 3815
A59: 43101 | D59: 41 | E59: 60195220 | F59: 91027645 | G59: 151222865 | H59: 27585
A60: 43466 | B60: 43831 | C60: 43831 | D60: 4 | E60: 2374705.4 | F60: 6751294.6 | G60: 9126000 | H60: 1840
C61: 43862 | D61: 1 | E61: 4388142.9 | F61: 142857.14 | G61: 4531000 | H61: 985
C62: 43891 | D62: 2 | E62: 2958000 | F62: 1882000 | G62: 4840000 | H62: 940
B63: 43831 | D63: 7 | E63: 9720848.2 | F63: 8776151.8 | G63: 18497000 | H63: 3765
B64: 43922 | C64: 43922 | D64: 4 | E64: 6532537 | F64: 11844963 | G64: 18377500 | H64: 4065
C65: 43952 | D65: 4 | E65: 8655299.5 | F65: 13936201 | G65: 22591500 | H65: 4380
C66: 43983 | D66: 1 | E66: 4394732.1 | F66: 3525267.9 | G66: 7920000 | H66: 1800
B67: 43922 | D67: 9 | E67: 19582569 | F67: 29306431 | G67: 48889000 | H67: 10245
B68: 44013 | C68: 44013 | D68: 13 | E68: 14590757 | F68: 46324243 | G68: 60915000 | H68: 12780
B69: 44013 | D69: 13 | E69: 14590757 | F69: 46324243 | G69: 60915000 | H69: 12780
B70: 44105 | C70: 44105 | D70: 17 | E70: 53441514 | F70: 21923486 | G70: 75365000 | H70: 17275
C71: 44136 | D71: 3 | E71: 6783123.6 | F71: 2176656.4 | G71: 8959780 | H71: 2030
C72: 44166 | D72: 5 | E72: 6171042.9 | F72: 14999807 | G72: 21170850 | H72: 4725
B73: 44105 | D73: 25 | E73: 66395681 | F73: 39099949 | G73: 105495630 | H73: 24030
A74: 43466 | D74: 54 | E74: 1.1028985e+08 | F74: 1.2350678e+08 | G74: 233796630 | H74: 50820
A75: 43831 | B75: 43831 | C75: 43831 | D75: 2 | E75: 3173025.9 | F75: 13158974 | G75: 16332000 | H75: 3660
C76: 43862 | D76: 1 | E76: 90000 | F76: 1338000 | G76: 1428000 | H76: 300
B77: 43831 | D77: 3 | E77: 3263025.9 | F77: 14496974 | G77: 17760000 | H77: 3960
B78: 44105 | C78: 44105 | D78: 3 | E78: 7179112.7 | F78: 11837247 | G78: 19016360 | H78: 3860
C79: 44136 | D79: 2 | E79: 4584000 | F79: 3922500 | G79: 8506500 | H79: 1640
C80: 44166 | D80: 1 | E80: 317920 | F80: 3826080 | G80: 4144000 | H80: 740
B81: 44105 | D81: 6 | E81: 12081033 | F81: 19585827 | G81: 31666860 | H81: 6240
A82: 43831 | D82: 9 | E82: 15344059 | F82: 34082801 | G82: 49426860 | H82: 10200
A83: 44197 | B83: 43831 | C83: 43831 | D83: 1 | E83: 4897500 | F83: 7500000 | G83: 12397500 | H83: 2755
C84: 43891 | D84: 3 | E84: 11185015 | F84: 6721984.8 | G84: 17907000 | H84: 4195
B85: 43831 | D85: 4 | E85: 16082515 | F85: 14221985 | G85: 30304500 | H85: 6950
B86: 43922 | C86: 43952 | D86: 1 | E86: 56278.571 | F86: 1428571.4 | G86: 1484850 | H86: 150
C87: 43983 | D87: 1 | E87: 6500000 | F87: 2500000 | G87: 9000000 | H87: 1800
B88: 43922 | D88: 2 | E88: 6556278.6 | F88: 3928571.4 | G88: 10484850 | H88: 1950
B89: 44013 | C89: 44075 | D89: 5 | E89: 19798140 | F89: 8510859.9 | G89: 28309000 | H89: 6335
B90: 44013 | D90: 5 | E90: 19798140 | F90: 8510859.9 | G90: 28309000 | H90: 6335
B91: 44105 | C91: 44105 | D91: 3 | E91: 5131910.7 | F91: 5389589.3 | G91: 10521500 | H91: 2330
C92: 44136 | D92: 4 | E92: 17403404 | F92: 21091346 | G92: 38494750 | H92: 6230
B93: 44105 | D93: 7 | E93: 22535315 | F93: 26480935 | G93: 49016250 | H93: 8560
A94: 44197 | D94: 18 | E94: 64972249 | F94: 53142351 | G94: 118114600 | H94: 23795
A95: 44562 | B95: 43831 | C95: 43831 | D95: 6 | E95: 20433457 | F95: 14501543 | G95: 34935000 | H95: 7210
C96: 43862 | D96: 11 | E96: 23778039 | F96: 21567461 | G96: 45345500 | H96: 10840
B97: 43831 | D97: 17 | E97: 44211497 | F97: 36069003 | G97: 80280500 | H97: 18050
A98: 44562 | D98: 17 | E98: 44211497 | F98: 36069003 | G98: 80280500 | H98: 18050
A99: Grand Total | D99: 288 | E99: 5.5141388e+08 | F99: 7.9479899e+08 | G99: 1346212870 | H99: 256050

Sheet Sheet8 - PivotTable2
A1: PivotTable2
A2: Floor No | B2: Saleable Area (Sum) | C2: Amount Received (Sum) | D2: Total vlue of Flat (Sum) | E2: Office No. (Count All)
A3: 11th | B3: 11015 | C3: 38656248 | D3: 64284450 | E3: 11
A4: 12th | B4: 10975 | C4: 34835773 | D4: 56156280 | E4: 12
A5: 13th | B5: 9605 | C5: 28183297 | D5: 51081545 | E5: 10
A6: 14th | B6: 8870 | C6: 40279459 | D6: 53782870 | E6: 10
A7: 15th | B7: 14320 | C7: 65342550 | D7: 86556880 | E7: 14
A8: 16th | B8: 11965 | C8: 42473540 | D8: 67003090 | E8: 13
A9: 17th | B9: 7330 | C9: 23913670 | D9: 38736495 | E9: 10
A10: 18th | B10: 6560 | C10: 21960203 | D10: 32528175 | E10: 9
A11: 19th | B11: 6835 | C11: 14949951 | D11: 38282385 | E11: 7
A12: 21th | B12: 10570 | C12: 33916866 | D12: 62247940 | E12: 11
A13: 22nd | B13: 13015 | C13: 41395412 | D13: 60787160 | E13: 12
A14: 23rd | B14: 14290 | C14: 23373664 | D14: 68639535 | E14: 14
... A24: Grand Total | B24: 256050 | C24: 7.9479899e+08 | D24: 1346212870 | E24: 288

Sheet Sheet8 - Table 1
G13: =GETPIVOTDATA("Total vlue of Flat",'Sheet8 - Table 1'!$A$2,"Floor No","21th")/10000000 -> #REF! | H13: =GETPIVOTDATA(" Amount Received ",'Sheet8 - Table 1'!$A$2,"Floor No","21th")/10000000 -> #REF!
G14: =GETPIVOTDATA("Total vlue of Flat",'Sheet8 - Table 1'!$A$2,"Floor No","22nd")/10000000 -> #REF! | H14: =GETPIVOTDATA(" Amount Received ",'Sheet8 - Table 1'!$A$2,"Floor No","22nd")/10000000 -> #REF!
G15: =GETPIVOTDATA("Total vlue of Flat",'Sheet8 - Table 1'!$A$2,"Floor No","23rd")/10000000 -> #REF! | H15: =GETPIVOTDATA(" Amount Received ",'Sheet8 - Table 1'!$A$2,"Floor No","23rd")/10000000 -> #REF!
G16: =GETPIVOTDATA("Total vlue of Flat",'Sheet8 - Table 1'!$A$2,"Floor No","24th")/10000000 -> #REF! | H16: =GETPIVOTDATA(" Amount Received ",'Sheet8 - Table 1'!$A$2,"Floor No","24th")/10000000 -> #REF!
G17: =GETPIVOTDATA("Total vlue of Flat",'Sheet8 - Table 1'!$A$2,"Floor No","25th")/10000000 -> #REF! | H17: =GETPIVOTDATA(" Amount Received ",'Sheet8 - Table 1'!$A$2,"Floor No","25th")/10000000 -> #REF!

Sheet Sheet9 - PivotTable2
A1: PivotTable2
A2: Floor No | B2: Sold/ Unsold (Count All) | C2: Saleable Area (Sum) | D2: Total vlue of Flat (Sum) | E2: Amount Received (Sum)
A3: 11th | B3: 11 | C3: 11535 | D3: 64284450 | E3: 38332499
A4: 12th | B4: 13 | C4: 12290 | D4: 61547780 | E4: 40227273
A5: 13th | B5: 10 | C5: 9605 | D5: 51081545 | E5: 28183297
A6: 14th | B6: 10 | C6: 8870 | D6: 53782870 | E6: 38732826
A7: 15th | B7: 14 | C7: 14390 | D7: 86556880 | E7: 66649512
A8: 16th | B8: 13 | C8: 11965 | D8: 67003090 | E8: 42473540
A9: 17th | B9: 12 | C9: 12115 | D9: 57760495 | E9: 31913670
A10: 18th | B10: 10 | C10: 8880 | D10: 44083445 | E10: 23420203
A11: 19th | B11: 8 | C11: 8880 | D11: 44340615 | E11: 15949951
A12: 21th | B12: 11 | C12: 10680 | D12: 62247940 | E12: 33916866
A13: 22nd | B13: 12 | C13: 13015 | D13: 60787160 | E13: 41395412
A14: 23rd | B14: 13 | C14: 13830 | D14: 66405035 | E14: 23173664
... A25: Grand Total | B25: 301 | C25: 261195 | D25: 1382227905 | E25: 8.2546385e+08

Sheet Sheet10 - PivotTable1 - PivotTa
A1: PivotTable1
A3: DOB | B3: Received (Count All) | C3: 3 (Sum) | D3: 4 (Sum) | E3: 2 (Sum)
A4: 1st | B4: 7 | C4: 46279480 | D4: 20574000 | E4: 12455
A5: 2nd | B5: 9 | C5: 66495408 | D5: 27859663 | E5: 17245
A6: 3rd | B6: 7 | C6: 50420911 | D6: 22815060 | E6: 13905
A7: 4th | B7: 7 | C7: 43732092 | D7: 21153500 | E7: 13905
A8: 5th | B8: 8 | C8: 56959351 | D8: 22129000 | E8: 15585
A9: 6th | B9: 7 | C9: 54499868 | D9: 24564203 | E9: 13905
A10: 7th | B10: 8 | C10: 60192725 | D10: 28037283 | E10: 15585
A11: Grand Total | B11: 53 | C11: 378579835 | D11: 167132709 | E11: 102585

Sheet Sheet10 - PivotTable1 - Table 1
A1: PivotTable1

Sheet Sheet10 - Table 1
G4: =GETPIVOTDATA(" 3",'Sheet10 - PivotTable1 - Table 1'!$A$4,"Floor","1st")/10000000 -> #REF! | H4: =GETPIVOTDATA(" 4",'Sheet10 - PivotTable1 - Table 1'!$A$4,"Floor","1st")/10000000 -> #REF!
G5: =GETPIVOTDATA(" 3",'Sheet10 - PivotTable1 - Table 1'!$A$4,"Floor","2nd")/10000000 -> #REF! | H5: =GETPIVOTDATA(" 4",'Sheet10 - PivotTable1 - Table 1'!$A$4,"Floor","2nd")/10000000 -> #REF!
G6: =GETPIVOTDATA(" 3",'Sheet10 - PivotTable1 - Table 1'!$A$4,"Floor","3rd")/10000000 -> #REF! | H6: =GETPIVOTDATA(" 4",'Sheet10 - PivotTable1 - Table 1'!$A$4,"Floor","3rd")/10000000 -> #REF!
G7: =GETPIVOTDATA(" 3",'Sheet10 - PivotTable1 - Table 1'!$A$4,"Floor","4th")/10000000 -> #REF! | H7: =GETPIVOTDATA(" 4",'Sheet10 - PivotTable1 - Table 1'!$A$4,"Floor","4th")/10000000 -> #REF!
G8: =GETPIVOTDATA(" 3",'Sheet10 - PivotTable1 - Table 1'!$A$4,"Floor","5th")/10000000 -> #REF! | H8: =GETPIVOTDATA(" 4",'Sheet10 - PivotTable1 - Table 1'!$A$4,"Floor","5th")/10000000 -> #REF!
G9: =GETPIVOTDATA(" 3",'Sheet10 - PivotTable1 - Table 1'!$A$4,"Floor","6th")/10000000 -> #REF! | H9: =GETPIVOTDATA(" 4",'Sheet10 - PivotTable1 - Table 1'!$A$4,"Floor","6th")/10000000 -> #REF!
G10: =GETPIVOTDATA(" 3",'Sheet10 - PivotTable1 - Table 1'!$A$4,"Floor","7th")/10000000 -> #REF! | H10: =GETPIVOTDATA(" 4",'Sheet10 - PivotTable1 - Table 1'!$A$4,"Floor","7th")/10000000 -> #REF!

Sheet Sheet12 - PivotTable2 - PivotTa
A1: PivotTable2
A3: Sales Value (Without Tax) | B3: Received (Count All) | C3: 2 (Sum) | D3: (Sum) | E3: Receivables (Sum) | F3: 4 (Count All)
A4: 1 | B4: 5 | C4: 8431338 | D4: 8431339 | E4: 1324.66 | F4: 1
A5: 2 | B5: 46 | C5: 61401218 | D5: 61614103 | E5: 11846.66 | F5: 4
A6: 3 | B6: 97 | C6: 86455533 | D6: 89042357 | E6: 16901.44 | F6: 3
A7: G | B7: 35 | C7: 90217593 | D7: 93434825 | E7: 12198.25 | F7: 8
A8: LG | B8: 31 | C8: 77675123 | D8: 77679817 | E8: 11066.67 | F8: 4
A9: Grand Total | B9: 214 | C9: 3.2418081e+08 | D9: 330202441 | E9: 53337.68 | F9: 20

Sheet Sheet12 - PivotTable2 - Table 1
A1: PivotTable2

Sheet Sheet13 - PivotTable3 - PivotTa
A1: PivotTable3
A3: DOB (Year) | B3: DOB (Qtr) | C3: DOB (Month) | D3: Received (Count All) | E3: 2 (Sum) | F3: (Sum) | G3: Receivables (Sum)
A4: 42370 | B4: 43922 | C4: 43952 | D4: 167 | E4: 2.4513024e+08 | F4: 250528875 | G4: 40134.32
C5: 43983 | D5: 47 | E5: 79050569 | F5: 79673566 | G5: 13203.36
B6: 43922 | D6: 214 | E6: 3.2418081e+08 | F6: 330202441 | G6: 53337.68
A7: 42370 | D7: 214 | E7: 3.2418081e+08 | F7: 330202441 | G7: 53337.68
A8: Grand Total | D8: 214 | E8: 3.2418081e+08 | F8: 330202441 | G8: 53337.68

Sheet Sheet13 - PivotTable3 - Table 1
A1: PivotTable3

Sheet Velocity
B3: Monthwise-Latest 12 months | C3: Area Sold | D3: Units Sold | E3: Rate | F3: Value Sold (Cr) | G3: Received (Cr) | H3: Receivables (Cr)
B18: Total | C18: =SUM(C12:C17) -> 0 | D18: =SUM(D12:D17) -> 0 | F18: =SUM(F12:F17) -> 0 | G18: =SUM(G12:G17) -> 0 | H18: =SUM(H12:H17) -> 0

Sheet Sheet16
C5: Particluars | D5: Oct-Dec-22 | E5: Jan- Feb 23 | F5: Total
C6: Area Sold (sq. ft.) - Projected | D6: 978 | E6: 978 | F6: =SUM(D6:E6) -> 1956
C7: Area Sold (sq. ft.) - Actual | D7: 7217 | E7: 742 | F7: =SUM(D7:E7) -> 7959
C9: Collection (Cr.) - Projected | D9: 4.34 | E9: 6.48 | F9: =SUM(D9:E9) -> 10.82
C10: Collection (Cr.) - Actual | D10: 11.47 | E10: 5.36 | F10: =SUM(D10:E10) -> 16.83
C12: Particulars | D12: Amt. (cr.)
C14: Incremental Collection Post disbursal is | D14: 16.83
C15: Stipulated SI | D15: 0.65
C17: ABFL Share | D17: =D14*D15 -> 10.9395
C19: ABFL Disbursal | D19: 28
C20: ABFL POS | D20: =28-6.18-0.47-1.9 -> 19.45
C21: Repaid | D21: =D19-D20 -> 8.55
C23: Short Cap | D23: =D17-D21 -> 2.3895

Sheet Sheet11 - PivotTable1 - PivotTa
A1: PivotTable1
A3: DOB (Month) | B3: DOB (YMD) | C3: Unit No (Count All) | D3: Saleable Area (Sum) | E3: Sales Value (Without Tax) (Sum) | F3: Received (Sum) | G3: Receivables (Sum)
A4: 43831 | B4: 44223 | C4: 3 | D4: 332.234 | E4: 16713845 | F4: 10315622 | G4: 6398223
A5: 43831 | C5: 3 | D5: 332.234 | E5: 16713845 | F5: 10315622 | G5: 6398223
A6: 43862 | B6: 44228 | C6: 1 | D6: 121.274 | E6: 6633688 | F6: 6166298 | G6: 467390
B7: 44229 | C7: 2 | D7: 226.754 | E7: 11242784 | F7: 10186524 | G7: 1056260
B8: 44230 | C8: 4 | D8: 469.302 | E8: 19752013 | F8: 18047374 | G8: 1704639
B9: 44231 | C9: 1 | D9: 121.274 | E9: 4062679 | F9: 3692795 | G9: 369884
B10: 44232 | C10: 1 | D10: 121.274 | E10: 6762117 | F10: 6249967 | G10: 512150
B11: 44233 | C11: 1 | D11: 121.274 | E11: 5978808 | F11: 5417311 | G11: 561497
B12: 44235 | C12: 2 | D12: 242.548 | E12: 9883831 | F12: 8968426 | G12: 915405
B13: 44236 | C13: 3 | D13: 363.822 | E13: 17668045 | F13: 16138059 | G13: 1529986
B14: 44238 | C14: 1 | D14: 109.613 | E14: 5042198 | F14: 4570859 | G14: 471339
B15: 44242 | C15: 3 | D15: 363.822 | E15: 12006126 | F15: 9281436 | G15: 2724690
B16: 44243 | C16: 1 | D16: 121.274 | E16: 4982300 | F16: 4520452 | G16: 461848
B17: 44244 | C17: 3 | D17: 363.822 | E17: 17099634 | F17: 14035930 | G17: 3063704
B18: 44245 | C18: 2 | D18: 242.548 | E18: 13012742 | F18: 12066093 | G18: 946649
... B24: 44255 | C24: 1 | D24: 121.274 | E24: 5881789 | F24: 5329993 | G24: 551796
A25: 43862 | C25: 35 | D25: 4153.959 | E25: 188021542 | F25: 166269959 | G25: 21751583
A26: 43891 | B26: 44256 | C26: 1 | D26: 121.274 | E26: 5457330 | F26: 4940017 | G26: 517313
B27: 44257 | C27: 1 | D27: 121.274 | E27: 4244590 | F27: 1819110 | G27: 2425480
B28: 44258 | C28: 2 | D28: 242.548 | E28: 9105252 | F28: 8338120 | G28: 767132
B29: 44261 | C29: 3 | D29: 348.028 | E29: 13061453 | F29: 11859717 | G29: 1201736
B30: 44263 | C30: 2 | D30: 242.548 | E30: 11278482 | F30: 7555370 | G30: 3723112
B31: 44264 | C31: 1 | D31: 105.48 | E31: 5221211 | F31: 4730737 | G31: 490474
B32: 44270 | C32: 4 | D32: 457.641 | E32: 18941397 | F32: 17337356 | G32: 1604041
B33: 44271 | C33: 2 | D33: 242.548 | E33: 12429251 | F33: 11613751 | G33: 815500
B34: 44272 | C34: 6 | D34: 711.85 | E34: 31959316 | F34: 29023230 | G34: 2936085.8
B35: 44273 | C35: 1 | D35: 121.274 | E35: 5821152 | F35: 2607391 | G35: 3213761
B36: 44276 | C36: 2 | D36: 242.548 | E36: 8125358 | F36: 3456308 | G36: 4669050
B37: 44278 | C37: 1 | D37: 121.274 | E37: 5321139 | F37: 2357384 | G37: 2963755
B38: 44279 | C38: 2 | D38: 242.548 | E38: 11869572 | F38: 10755377 | G38: 1114194.6
... B43: 44286 | C43: 1 | D43: 121.274 | E43: 5966681 | F43: 4724835 | G43: 1241846
A44: 43891 | C44: 37 | D44: 4400.64 | E44: 193391376 | F44: 1.5308895e+08 | G44: 40302425
A45: 43922 | B45: 44287 | C45: 2 | D45: 242.548 | E45: 9388305 | F45: 8359084.5 | G45: 1029220.6
B46: 44290 | C46: 1 | D46: 121.274 | E46: 5863719 | F46: 5313731 | G46: 549988
B47: 44291 | C47: 6 | D47: 727.644 | E47: 33840660 | F47: 17546209 | G47: 16294451
B48: 44293 | C48: 1 | D48: 121.274 | E48: 6245611 | F48: 5650265.3 | G48: 595345.74
B49: 44298 | C49: 2 | D49: 242.548 | E49: 11581667 | F49: 7755469 | G49: 3826198
B50: 44299 | C50: 2 | D50: 242.548 | E50: 9520009 | F50: 8640773 | G50: 879236
B51: 44300 | C51: 2 | D51: 242.548 | E51: 12202226 | F51: 8420110 | G51: 3782116
B52: 44301 | C52: 1 | D52: 121.274 | E52: 6003063 | F52: 5439136 | G52: 563927
B53: 44302 | C53: 1 | D53: 121.274 | E53: 4002042 | F53: 1698000 | G53: 2304042
B54: 44312 | C54: 2 | D54: 242.548 | E54: 11157208 | F54: 10114244 | G54: 1042964
B55: 44315 | C55: 1 | D55: 121.274 | E55: 6427401 | F55: 2910515 | G55: 3516886
A56: 43922 | C56: 21 | D56: 2546.754 | E56: 116231911 | F56: 81847537 | G56: 34384374
A57: 43983 | B57: 44351 | C57: 1 | D57: 121.274 | E57: 5672955 | F57: 2533292 | G57: 3139663
B58: 44354 | C58: 1 | D58: 121.274 | E58: 4002042 | F58: 3638218 | G58: 363824
B59: 44355 | C59: 1 | D59: 121.274 | E59: 4438628 | F59: 1697836 | G59: 2740792
B60: 44361 | C60: 1 | D60: 121.274 | E60: 4815184 | F60: 2104407 | G60: 2710777
B61: 44364 | C61: 1 | D61: 121.274 | E61: 5490923 | F61: 4978210 | G61: 512713
B62: 44368 | C62: 1 | D62: 121.274 | E62: 4002042 | F62: 3153123 | G62: 848919
B63: 44372 | C63: 1 | D63: 121.274 | E63: 5457330 | F63: 4947979 | G63: 509351
B64: 44375 | C64: 1 | D64: 121.274 | E64: 5736260 | F64: 2564945 | G64: 3171315
A65: 43983 | C65: 8 | D65: 970.192 | E65: 39615364 | F65: 25618010 | G65: 13997354
A66: 44013 | B66: 44379 | C66: 2 | D66: 226.754 | E66: 11109614 | F66: 7155637 | G66: 3953977
B67: 44380 | C67: 1 | D67: 121.274 | E67: 5585032 | F67: 2489330 | G67: 3095702
B68: 44383 | C68: 1 | D68: 121.274 | E68: 6609433 | F68: 2728665 | G68: 3880768
B69: 44403 | C69: 1 | D69: 121.274 | E69: 6235303 | F69: 5373000 | G69: 862303
A70: 44013 | C70: 5 | D70: 590.576 | E70: 29539382 | F70: 17746632 | G70: 11792750
A71: 44044 | B71: 44417 | C71: 1 | D71: 121.274 | E71: 5795927 | F71: 3924794 | G71: 1871133
B72: 44420 | C72: 1 | D72: 121.274 | E72: 3820131 | F72: 821376 | G72: 2998755
B73: 44424 | C73: 1 | D73: 121.274 | E73: 6091350 | F73: 5518597 | G73: 572753
A74: 44044 | C74: 3 | D74: 363.822 | E74: 15707408 | F74: 10264767 | G74: 5442641
A75: 44075 | B75: 44446 | C75: 1 | D75: 121.274 | E75: 5699878 | F75: 5166274 | G75: 533604
A76: 44075 | C76: 1 | D76: 121.274 | E76: 5699878 | F76: 5166274 | G76: 533604
A77: 44105 | B77: 44471 | C77: 1 | D77: 121.274 | E77: 5699878 | F77: 5166274 | G77: 533604
B78: 44472 | C78: 1 | D78: 121.274 | E78: 4139688 | F78: 3762103 | G78: 377585
B79: 44480 | C79: 1 | D79: 121.274 | E79: 5497472 | F79: 4983835 | G79: 513637
A80: 44105 | C80: 3 | D80: 363.822 | E80: 15337038 | F80: 13912212 | G80: 1424826
A81: Grand Total | C81: 116 | D81: 13843.273 | E81: 620257744 | F81: 4.8422996e+08 | G81: 1.3602778e+08

Sheet Sheet11 - PivotTable1 - Table 1
A1: PivotTable1

Sheet Sold- Prime
A2: S No. | B2: Unit No | C2: Customer Name | D2: DOB | E2: Saleable Area | F2: Sales Value (Without Tax) | G2: Received | H2: Receivables
A3: 1 | B3: PLOT NO - 01 | C3: Amar Singh Bhadauria | D3: 44355 | E3: 121.274 | F3: 4438628.2 | G3: 1697836 | H3: =F3-G3 -> 2740792.2 | I3: =G3/F3 -> 0.38251368
A4: 2 | B4: PLOT NO - 02 | C4: Abhishek Yadav | D4: 44236 | E4: 121.274 | F4: 5509114.2 | G4: 4994581 | H4: =F4-G4 -> 514533.2 | I4: =G4/F4 -> 0.90660328
A5: 3 | B5: PLOT NO - 03 | C5: Anju Yadav | D5: 44272 | E5: 121.274 | F5: 5881789.2 | G5: 5376562 | H5: =F5-G5 -> 505227.2 | I5: =G5/F5 -> 0.91410314
A6: 4 | B6: PLOT NO - 04 | C6: Raj Kumar | D6: 44272 | E6: 121.274 | F6: 5881789.2 | G6: 5329694 | H6: =F6-G6 -> 552095.2 | I6: =G6/F6 -> 0.90613482
A7: 5 | B7: PLOT NO - 05 | C7: Rajpal Singh | D7: 44287 | E7: 121.274 | F7: 4002042.2 | G7: 3638218 | H7: =F7-G7 -> 363824.2 | I7: =G7/F7 -> 0.90909036
A8: 6 | B8: PLOT NO - 06 | C8: Harsh Singh | D8: 44372 | E8: 121.274 | F8: 5457330.2 | G8: 4947979 | H8: =F8-G8 -> 509351.2 | I8: =G8/F8 -> 0.9066666
A9: 7 | B9: PLOT NO - 07 | C9: Santosh | D9: 44253 | E9: 121.274 | F9: 5639241.2 | G9: 5111698 | H9: =F9-G9 -> 527543.2 | I9: =G9/F9 -> 0.90645139
A10: 8 | B10: PLOT NO - 08 | C10: Harsh Rathore | D10: 44244 | E10: 121.274 | F10: 5821152.2 | G10: 5275417 | H10: =F10-G10 -> 545735.2 | I10: =G10/F10 -> 0.90624963
A11: 9 | B11: PLOT NO - 09 | C11: Kunal Chopra | D11: 44236 | E11: 121.274 | F11: 5821152.2 | G11: 5275417 | H11: =F11-G11 -> 545735.2 | I11: =G11/F11 -> 0.90624963
A12: 10 | B12: PLOT NO - 10 | C12: Ankur Jain | D12: 44354 | E12: 121.274 | F12: 4002042.2 | G12: 3638218 | H12: =F12-G12 -> 363824.2 | I12: =G12/F12 -> 0.90909036
A13: 11 | B13: PLOT NO - 11 | C13: Vinay Kumar | D13: 44229 | E13: 121.274 | F13: 5863355.6 | G13: 5313398 | H13: =F13-G13 -> 549957.55 | I13: =G13/F13 -> 0.9062043
A14: 12 | B14: PLOT NO - 12 | C14: Nitish Kumar Chand | D14: 44223 | E14: 121.274 | F14: 6124337.2 | G14: 5548288 | H14: =F14-G14 -> 576049.2 | I14: =G14/F14 -> 0.90594097
... A182: 180 | B182: PLOT NO - 216 | C182: Ashok Kumar Grover | D182: 44872 | E182: 128.4 | F182: 5432476 | G182: 2100882 | H182: =F182-G182 -> 3331594 | I182: =G182/F182 -> 0.38672642
E183: =SUBTOTAL(9,E3:E182) -> 21680.853 | F183: =SUBTOTAL(9,F3:F182) -> 9.6897866e+08 | G183: =SUBTOTAL(9,G3:G182) -> 6.7169764e+08 | H183: =SUBTOTAL(9,H3:H182) -> 2.9728101e+08
A185: 116 | E185: 13843.273 | F185: 620257744 | G185: 4.8422996e+08 | H185: 1.3602778e+08
H186: =H183-H185 -> 1.6125323e+08
H187: =H186*0.65 -> 1.048146e+08

Sheet Unsold-Prime
A1: S.NO | B1: PLOT NO | C1: PLOT AREA (SQ.YD) | D1: INVENTORY STATUS | E1: DEVELOPER / OWNER
A2: 1 | B2: PLOT NO - 26 | C2: 121.2744 | D2: UNDER FREEZE | PLEDGE | E2: OWNER - DHARAM SINGH
A3: =A2+1 -> 2 | B3: PLOT NO - 27 | C3: 121.2744 | D3: UNDER FREEZE | PLEDGE | E3: OWNER - DHARAM SINGH
A4: =A3+1 -> 3 | B4: PLOT NO - 29 | C4: 121.2744 | D4: UNDER FREEZE | PLEDGE | E4: OWNER - DHARAM SINGH
A5: =A4+1 -> 4 | B5: PLOT NO - 32 | C5: 121.2744 | D5: UNDER FREEZE | PLEDGE | E5: OWNER - DHARAM SINGH
A6: =A5+1 -> 5 | B6: PLOT NO - 34 | C6: 121.2744 | D6: UNDER FREEZE | PLEDGE | E6: OWNER - DHARAM SINGH
A7: =A6+1 -> 6 | B7: PLOT NO - 36 | C7: 121.2744 | D7: UNDER FREEZE | PLEDGE | E7: OWNER - DHARAM SINGH
A8: =A7+1 -> 7 | B8: PLOT NO - 41 | C8: 121.2744 | D8: UNDER FREEZE | PLEDGE | E8: OWNER - DHARAM SINGH
A9: =A8+1 -> 8 | B9: PLOT NO - 53 | C9: 121.2744 | D9: UNDER FREEZE | PLEDGE | E9: OWNER - DHARAM SINGH
A10: =A9+1 -> 9 | B10: PLOT NO - 54 | C10: 121.2744 | D10: UNDER FREEZE | PLEDGE | E10: OWNER - DHARAM SINGH
A11: =A10+1 -> 10 | B11: PLOT NO - 57 | C11: 121.2744 | D11: UNDER FREEZE | PLEDGE | E11: OWNER - DHARAM SINGH
A12: =A11+1 -> 11 | B12: PLOT NO - 59 | C12: 121.2744 | D12: UNDER FREEZE | PLEDGE | E12: OWNER - DHARAM SINGH
A13: =A12+1 -> 12 | B13: PLOT NO - 60 | C13: 121.2744 | D13: UNDER FREEZE | PLEDGE | E13: OWNER - DHARAM SINGH
A14: =A13+1 -> 13 | B14: PLOT NO - 63 | C14: 121.2744 | D14: UNDER FREEZE | PLEDGE | E14: OWNER - DHARAM SINGH
... A37: =A36+1 -> 36 | B37: PLOT NO - 215 | C37: 121.2744 | D37: UNDER FREEZE | PLEDGE | E37: OWNER - RAVINDER SINGH
A38: Total | C38: =SUM(C2:C37) -> 4425.3017
A41: S.NO | B41: PLOT NO | C41: PLOT AREA (SQ.YD) | D41: INVENTORY STATUS | E41: Developer
A42: 1 | B42: Unit No. 1 | C42: 80 | D42: UNDER FREEZE | PLEDGE | E42: Commercial Unit
A43: =A42+1 -> 2 | B43: Unit No. 2 | C43: 80 | D43: UNDER FREEZE | PLEDGE | E43: Commercial Unit
A44: =A43+1 -> 3 | B44: Unit No. 3 | C44: 80 | D44: UNDER FREEZE | PLEDGE | E44: Commercial Unit
A45: =A44+1 -> 4 | B45: Unit No. 4 | C45: 80 | D45: UNDER FREEZE | PLEDGE | E45: Commercial Unit
A46: =A45+1 -> 5 | B46: Unit No. 5 | C46: 80 | D46: UNDER FREEZE | PLEDGE | E46: Commercial Unit
A47: =A46+1 -> 6 | B47: Unit No. 6 | C47: 80 | D47: UNDER FREEZE | PLEDGE | E47: Commercial Unit
A48: =A47+1 -> 7 | B48: Unit No. 7 | C48: 80 | D48: UNDER FREEZE | PLEDGE | E48: Commercial Unit
A49: =A48+1 -> 8 | B49: Unit No. 8 | C49: 80 | D49: UNDER FREEZE | PLEDGE | E49: Commercial Unit
A50: =A49+1 -> 9 | B50: Unit No. 9 | C50: 80 | D50: UNDER FREEZE | PLEDGE | E50: Commercial Unit
A51: =A50+1 -> 10 | B51: Unit No. 10 | C51: 80 | D51: UNDER FREEZE | PLEDGE | E51: Commercial Unit
A52: =A51+1 -> 11 | B52: Unit No. 11 | C52: 80 | D52: UNDER FREEZE | PLEDGE | E52: Commercial Unit
A53: =A52+1 -> 12 | B53: Unit No. 12 | C53: 80 | D53: UNDER FREEZE | PLEDGE | E53: Commercial Unit
A54: =A53+1 -> 13 | B54: Unit No. 13 | C54: 80 | D54: UNDER FREEZE | PLEDGE | E54: Commercial Unit
... A65: =A64+1 -> 24 | B65: Unit No. 24 | C65: 80 | D65: UNDER FREEZE | PLEDGE | E65: Commercial Unit
A66: Total | C66: =SUM(C42:C65) -> 1920

Sheet Sheet14 - PivotTable1
A1: PivotTable1
A2: Saleable Area | B2: Unit No (Count All) | C2: Received (Sum) | D2: Sales Value (Without Tax) (Sum) | E2: Saleable Area (Sum)
A3: 112.393 | B3: 1 | C3: 2736918 | D3: 5394864 | E3: 112.393
A4: 120.138 | B4: 1 | C4: 1000000 | D4: 7064114 | E4: 120.138
A5: 121.352 | B5: 40 | C5: 80262969 | D5: 250232363 | E5: 4854.08
A6: 124.022 | B6: 11 | C6: 12850346 | D6: 63080442 | E6: 1364.242
A7: 127.618 | B7: 9 | C7: 21616208 | D7: 51483908 | E7: 1148.562
A8: 129.902 | B8: 5 | C8: 12128737 | D8: 34333099 | E8: 649.51
A9: 138.398 | B9: 1 | C9: 3788000 | D9: 7575353 | E9: 138.398
A10: 139.886 | B10: 1 | C10: 3000000 | D10: 7987491 | E10: 139.886
A11: 139.887 | B11: 2 | C11: 5405879 | D11: 16898349 | E11: 279.774
A12: 164.292 | B12: 1 | C12: 2700000 | D12: 10723339 | E12: 164.292
A13: Grand Total | B13: 72 | C13: 1.4548906e+08 | D13: 454773322 | E13: 8971.275

Sheet Sheet15 - PivotTable2
A1: PivotTable2
A2: PLOT AREA (SQ.YD) | B2: PLOT AREA (SQ.YD) (Sum)
A3: 112.391 | B3: 112.391
A4: 121.352 | B4: 2184.336
A5: 124.022 | B5: 868.154
A6: 126.405 | B6: 126.405
A7: 129.902 | B7: 129.902
A8: 138.398 | B8: 553.592
A9: 139.887 | B9: 419.661
A10: 168.777 | B10: 168.777
A11: 177.623 | B11: 177.623
A12: Grand Total | B12: 4740.841

Sheet Sheet15 - Table 1
C4: =GETPIVOTDATA("PLOT AREA (SQ.YD)",'Sheet15 - Table 1'!$A$2,"PLOT AREA (SQ.YD)",112.391)/'Sheet15 - Table 1'!$A$3 -> #REF!
C5: =GETPIVOTDATA("PLOT AREA (SQ.YD)",'Sheet15 - Table 1'!$A$2,"PLOT AREA (SQ.YD)",121.352)/'Sheet15 - Table 1'!$A$4 -> #REF!
C6: =GETPIVOTDATA("PLOT AREA (SQ.YD)",'Sheet15 - Table 1'!$A$2,"PLOT AREA (SQ.YD)",124.022)/'Sheet15 - Table 1'!$A$5 -> #REF!
C7: =GETPIVOTDATA("PLOT AREA (SQ.YD)",'Sheet15 - Table 1'!$A$2,"PLOT AREA (SQ.YD)",126.405)/'Sheet15 - Table 1'!$A$6 -> #REF!
C8: =GETPIVOTDATA("PLOT AREA (SQ.YD)",'Sheet15 - Table 1'!$A$2,"PLOT AREA (SQ.YD)",129.902)/'Sheet15 - Table 1'!$A$7 -> #REF!
C9: =GETPIVOTDATA("PLOT AREA (SQ.YD)",'Sheet15 - Table 1'!$A$2,"PLOT AREA (SQ.YD)",138.398)/'Sheet15 - Table 1'!$A$8 -> #REF!
C10: =GETPIVOTDATA("PLOT AREA (SQ.YD)",'Sheet15 - Table 1'!$A$2,"PLOT AREA (SQ.YD)",139.887)/'Sheet15 - Table 1'!$A$9 -> #REF!
C11: =GETPIVOTDATA("PLOT AREA (SQ.YD)",'Sheet15 - Table 1'!$A$2,"PLOT AREA (SQ.YD)",168.777)/'Sheet15 - Table 1'!$A$10 -> #REF!
C12: =GETPIVOTDATA("PLOT AREA (SQ.YD)",'Sheet15 - Table 1'!$A$2,"PLOT AREA (SQ.YD)",177.623)/'Sheet15 - Table 1'!$A$11 -> #REF!

Sheet Unsold 
B3: S.No. | C3: Floor No | D3: Office No. | E3: Area (sq.ft.)
B4: 1 | C4: 1st | D4: Floor | E4: 16000
B5: 2 | C5: 2nd | D5: 201 | E5: 2150
B6: =B5+1 -> 3 | C6: 2nd | D6: 202 | E6: 1800
B7: =B6+1 -> 4 | C7: 2nd | D7: 203A | E7: 850
B8: =B7+1 -> 5 | C8: 2nd | D8: 203B | E8: 660
B9: =B8+1 -> 6 | C9: 2nd | D9: 204 | E9: 655
B10: =B9+1 -> 7 | C10: 2nd | D10: 205A | E10: 715
B11: =B10+1 -> 8 | C11: 2nd | D11: 205B | E11: 710
B12: =B11+1 -> 9 | C12: 2nd | D12: 208 | E12: 740
B13: =B12+1 -> 10 | C13: 2nd | D13: 209 | E13: 985
B14: =B13+1 -> 11 | C14: 2nd | D14: 210 | E14: 1450
B15: =B14+1 -> 12 | C15: 2nd | D15: 211 | E15: 1175
B16: =B15+1 -> 13 | C16: 2nd | D16: 214A | E16: 1440
B17: =B16+1 -> 14 | C17: 2nd | D17: 214B | E17: 1275
B18: =B17+1 -> 15 | C18: 4th | D18: 410 | E18: 1450
B19: =B18+1 -> 16 | C19: 4th | D19: 411 | E19: 1175
B20: =B19+1 -> 17 | C20: 4th | D20: 414A | E20: 1440
B21: =B20+1 -> 18 | C21: 4th | D21: 402 | E21: 1800
B22: =B21+1 -> 19 | C22: 6th | D22: 602 | E22: 860
B23: =B22+1 -> 20 | C23: 6th | D23: 605A | E23: 510
B24: =B23+1 -> 21 | C24: 6th | D24: 611 | E24: 1175
C25: 6th | D25: 612 | E25: 1030
B26: =B24+1 -> 22 | C26: 7th | D26: 702 | E26: 860
B27: =B26+1 -> 23 | C27: 7th | D27: 705A | E27: 510
B28: =B27+1 -> 24 | C28: 8th | D28: Shared Space | E28: 3530
B29: =B28+1 -> 25 | C29: 9th | D29: 901 | E29: 2220
B30: =B29+1 -> 26 | C30: 9th | D30: 909 | E30: 985
B31: =B30+1 -> 27 | C31: 9th | D31: 910 | E31: 1520
B32: =B31+1 -> 28 | C32: 9th | D32: 914A | E32: 1440
B33: =B32+1 -> 29 | C33: 9th | D33: 914B | E33: 1315
B34: =B33+1 -> 30 | C34: 10th | D34: SERVICE FLOOR | E34: 0
B35: =B34+1 -> 31 | C35: 11th | D35: 1102 | E35: 860
B36: =B35+1 -> 32 | C36: 11th | D36: 1105A | E36: 510
B37: =B36+1 -> 33 | C37: 11th | D37: 1110 | E37: 1520
C38: 11th | D38: 1114B | E38: 1315
B39: =B37+1 -> 34 | C39: 12th | D39: 1210 | E39: 1520
B40: =B39+1 -> 35 | C40: 12th | D40: 1211 | E40: 1175
B41: 36 | C41: 12th | D41: 1212 | E41: 1090
B42: =B41+1 -> 37 | C42: 12th | D42: 1214A | E42: 1440
B43: =B42+1 -> 38 | C43: 13th | D43: 1304 | E43: 655
B44: =B43+1 -> 39 | C44: 13th | D44: 1305-A | E44: 715
B45: =B44+1 -> 40 | C45: 13th | D45: 1310 | E45: 1520
B46: =B45+1 -> 41 | C46: 13th | D46: 1311 | E46: 1175
B47: =B46+1 -> 42 | C47: 13th | D47: 1312 | E47: 1090
B48: =B47+1 -> 43 | C48: 13th | D48: 1314-A | E48: 1440
B49: =B48+1 -> 44 | C49: 13th | D49: 1314-B | E49: 1315
B50: =B49+1 -> 45 | C50: 14th | D50: 1402 | E50: 860
B51: =B50+1 -> 46 | C51: 14th | D51: 1405A | E51: 510
B52: =B51+1 -> 47 | C52: 14th | D52: 1410 | E52: 1520
B53: =B52+1 -> 48 | C53: 14th | D53: 1411 | E53: 1175
B54: =B53+1 -> 49 | C54: 14th | D54: 1414A | E54: 1440
B55: =B54+1 -> 50 | C55: 14th | D55: 1414B | E55: 1315
B56: =B55+1 -> 51 | C56: 15th | D56: 1502 | E56: 860
B57: =B56+1 -> 52 | C57: 15th | D57: 1505A | E57: 510
B58: =B57+1 -> 53 | C58: 16th | D58: 1610 | E58: 1520
B59: =B58+1 -> 54 | C59: 16th | D59: 1611 | E59: 1175
B60: =B59+1 -> 55 | C60: 16th | D60: 1614A | E60: 1440
B61: =B60+1 -> 56 | C61: 16th | D61: 1614B | E61: 1315
B62: =B61+1 -> 57 | C62: 17th | D62: 1710 | E62: 1520
B63: =B62+1 -> 58 | C63: 17th | D63: 1711 | E63: 1175
B64: =B63+1 -> 59 | C64: 17th | D64: 1714A | E64: 1440
B65: =B64+1 -> 60 | C65: 17th | D65: 1714B | E65: 1315
B66: =B65+1 -> 61 | C66: 18th | D66: 1802 | E66: 860
B67: =B66+1 -> 62 | C67: 18th | D67: 1805A | E67: 510
B68: =B67+1 -> 63 | C68: 18th | D68: 1810 | E68: 1520
B69: =B68+1 -> 64 | C69: 18th | D69: 1811 | E69: 1175
B70: =B69+1 -> 65 | C70: 18th | D70: 1814A | E70: 1440
B71: =B70+1 -> 66 | C71: 18th | D71: 1814B | E71: 1315
B72: =B71+1 -> 67 | C72: 19th | D72: 1902 | E72: 860
B73: =B72+1 -> 68 | C73: 19th | D73: 1905A | E73: 510
B74: =B73+1 -> 69 | C74: 19th | D74: 1910 | E74: 1520
B75: =B74+1 -> 70 | C75: 19th | D75: 1911 | E75: 1175
B76: =B75+1 -> 71 | C76: 19th | D76: 1914A | E76: 1440
B77: =B76+1 -> 72 | C77: 19th | D77: 1914B | E77: 1315
B78: =B77+1 -> 73 | C78: 20th | D78: SERVICE FLOOR | E78: 0
B79: =B78+1 -> 74 | C79: 21st | D79: 2110 | E79: 1520
B80: =B79+1 -> 75 | C80: 21st | D80: 2111 | E80: 1175
B81: =B80+1 -> 76 | C81: 21st | D81: 2114A | E81: 1440
C82: 21st | D82: 2105A | E82: 715
C83: 21st | D83: 2105B | E83: 710
B84: =B81+1 -> 77 | C84: 21st | D84: 2114B | E84: 1315
B85: =B84+1 -> 78 | C85: 22nd | D85: 2202 | E85: 860
B86: =B85+1 -> 79 | C86: 22nd | D86: 2203B | E86: 660
B87: =B86+1 -> 80 | C87: 22nd | D87: 2204 | E87: 655
B88: =B87+1 -> 81 | C88: 22nd | D88: 2205A | E88: 510
B89: =B88+1 -> 82 | C89: 23rd | D89: 2302 | E89: 860
B90: =B89+1 -> 83 | C90: 23rd | D90: 2305A | E90: 510
B91: =B90+1 -> 84 | C91: 23rd | D91: 2306A | E91: 500
B92: =B91+1 -> 85 | C92: 24th | D92: 2406A | E92: 500
B93: =B92+1 -> 86 | C93: 24th | D93: 2410 | E93: 1520
B94: =B93+1 -> 87 | C94: 24th | D94: 2414A | E94: 1440
B95: =B94+1 -> 88 | C95: 24th | D95: 2414B | E95: 1315
B96: =B95+1 -> 89 | C96: 25th | D96: 2510 | E96: 1520
B97: =B96+1 -> 90 | C97: 25th | D97: 2511 | E97: 1175
B98: =B97+1 -> 91 | C98: 25th | D98: 2514A | E98: 1440
B99: 92 | C99: 26th | D99: Floor | E99: 17500
B100: =B99+1 -> 93 | C100: 27th | D100: Floor | E100: 17500
E101: =SUM(E4:E100) -> 157835
E102: 419030
...

Sheet Collection Velocity
A2: Collection Report
A3: Latest 12 Month | B3: Collection (in Crs) | C3: Units Sold
A17: Total | B17: =SUM(B4:B15) -> 0 | C17: =SUM(C4:C15) -> 0

Sheet Sheet5
B2: S.No. | C2: Name | D2: Allotment Date | E2: Tower | F2: Unit No. | G2: Unit | H2: Area | I2: Unit Cost | J2: Avg
B3: 1 | C3: Ms. Dimple | D3: 41201 | E3: 6th Floor | F3: OFFICE-50 | G3: OFFICE-50-6th Floor | H3: 446.73 | I3: 2498426 | J3: 5592.6981
B4: 2 | C4: Mrs. Renu Bala Kohli | D4: 41202 | E4: 6th Floor | F4: OFFICE-44 | G4: OFFICE-44-6th Floor | H4: 446.73 | I4: 2453753 | J4: 5492.6981
B5: 3 | C5: Mrs. Renu Bala Kohli | D5: 41202 | E5: 6th Floor | F5: OFFICE-45 | G5: OFFICE-45-6th Floor | H5: 446.73 | I5: 2453753 | J5: 5492.6981
B6: 4 | C6: Mr. Vikram Nanda | D6: 41211 | E6: 6th Floor | F6: OFFICE-58 | G6: OFFICE-58-6th Floor | H6: 446.73 | I6: 2498426 | J6: 5592.6981
B7: 5 | C7: Mr. Ramesh Dudani | D7: 41234 | E7: 6th Floor | F7: OFFICE-51 | G7: OFFICE-51-6th Floor | H7: 446.73 | I7: 2434156 | J7: 5448.8304
B8: 6 | C8: Mr. Sanjeev Kumar Seth | D8: 41235 | E8: 9th Floor | F8: OFFICE-14 | G8: OFFICE-14-9th Floor | H8: 446.73 | I8: 2498426 | J8: 5592.6981
B9: 7 | C9: Mrs. Kamalpreet Randhawa | D9: 41242 | E9: 6th Floor | F9: OFFICE-57 | G9: OFFICE-57-6th Floor | H9: 446.73 | I9: 2498426 | J9: 5592.6981
B10: 8 | C10: Mrs. Gulwant Kaur | D10: 41242 | E10: 6th Floor | F10: OFFICE-54 | G10: OFFICE-54-6th Floor | H10: 446.73 | I10: 2498426 | J10: 5592.6981
B11: 9 | C11: Mrs. Sudha Batra | D11: 41242 | E11: 4th Floor | F11: OFFICE-55 | G11: OFFICE-55-4th Floor | H11: 950 | I11: 4988000 | J11: 5250.5263
B12: 10 | C12: Mr. Hemant Kumar | D12: 41243 | E12: 4th Floor | F12: OFFICE-15 | G12: OFFICE-15-4th Floor | H12: 712.49 | I12: 3865762 | J12: 5425.707
B13: 11 | C13: Mr. Jagdish Kumar Arora | D13: 41243 | E13: 6th Floor | F13: OFFICE-35 | G13: OFFICE-35-6th Floor | H13: 446.73 | I13: 2605529 | J13: 5832.4469
B14: 12 | C14: Mr. Manjit Singh | D14: 41247 | E14: 9th Floor | F14: OFFICE-60 | G14: OFFICE-60-9th Floor | H14: 446.73 | I14: 2605530 | J14: 5832.4491
... B458: 456 | C458: Dr. Gurjeet Kaur Raikhy | D458: 44496 | E458: Ground Floor | F458: UNIT-10 | G458: UNIT-10-Ground Floor | H458: 919.12 | I458: 5785860 | J458: 6294.9996
C459: TOTAL | H459: 222760.92 | I459: 1492304708
E461: Sold units | F461: Sold Area | G461: Sale Value (Cr.) | H461: Average Rate/sq.ft
E462: 294 | F462: 142963 | G462: 104.51 | H462: =G462*10000000/F462 -> 7310.2831
E463: 162 | F463: 79798 | G463: 44.72 | H463: =G463*10000000/F463 -> 5604.1505
E464: =SUM(E462:E463) -> 456 | F464: =SUM(F462:F463) -> 222761 | G464: =SUM(G462:G463) -> 149.23 | H464: =G464*10000000/F464 -> 6699.108

Sheet Sheet4
D4: Company | E4: SBL Builders Private Limited
D5: Project | E5: Grande Next One
D6: Location | E6: Zirakpur, Punjab
D7: Lender | E7: DMI Finance Ltd.
D9: Sold Receivables | E9: 25.91
D10: Unsold Receivables | E10: 62.14
D11: Total Receivables | E11: =E9+E10 -> 88.05
D13: Total Cost | E13: =108.94+30.77 -> 139.71
D14: Cost Incurred | E14: 108.94
D15: Cost to be incurred | E15: =E13-E14 -> 30.77
D17: Loan POS | E17: 29.72
D19: Net Receivables | E19: =E11-E15-E17 -> 27.56

Sheet Sheet6
A1: Name | B1: Allotment Date | C1: Tower | D1: Unit No. | E1: Area | F1: Unit Cost | G1: Received | H1: Receivables
A2: Mr. Himanshu Khandelwal | B2: 41281 | C2: 9th Floor | D2: OFFICE-63 | E2: 446.73 | F2: 2030530 | G2: 2044355 | H2: -13825
A3: Mr. Rakesh Chadha | B3: 41285 | C3: 9th Floor | D3: OFFICE-66 | E3: 446.73 | F3: 2498426 | G3: 2510803 | H3: -12377
A4: Mr. Surinder Kumar | B4: 41286 | C4: 6th Floor | D4: OFFICE-37 | E4: 446.73 | F4: 2605529 | G4: 2528177 | H4: 77352
A5: Mr. Kuldeep Kumar Sharma | B5: 41289 | C5: 6th Floor | D5: OFFICE-36 | E5: 446.73 | F5: 2005530 | G5: 1983195 | H5: 22335
A6: Mr. Ashok Kumar Singh | B6: 41289 | C6: 6th Floor | D6: OFFICE-26 | E6: 446.73 | F6: 2005530 | G6: 1983193 | H6: 22337
A7: Mr. Gurminder Singh Multani | B7: 41302 | C7: 9th Floor | D7: OFFICE-02 | E7: 446.73 | F7: 2699343 | G7: 2565436 | H7: 133907
A8: Mrs. Ravneet Garg | B8: 41318 | C8: 8th Floor | D8: OFFICE-63 | E8: 447 | F8: 1526356 | G8: 501697 | H8: 1024659
A9: Mr. Gurpal Singh | B9: 41358 | C9: 10th Floor | D9: OFFICE-11 | E9: 446.73 | F9: 2180669 | G9: 2158374 | H9: 22295
A10: Mrs. Prerna Bansal | B10: 41363 | C10: 9th Floor | D10: OFFICE-52 | E10: 446.73 | F10: 2609997 | G10: 2622813 | H10: -12816
A11: Ms. Esha Sodhi | B11: 41422 | C11: 11th Floor | D11: OFFICE-09 | E11: 446.73 | F11: 1111445 | G11: 1089107 | H11: 22338
A12: Mr. Chander bir Singh Chowdhry | B12: 41482 | C12: 12th Floor | D12: OFFICE-01 | E12: 447 | F12: 1523277 | G12: 1510574 | H12: 12703
A13: Mrs. Usha Rani | B13: 41510 | C13: 12th Floor | D13: OFFICE-15 | E13: 446.73 | F13: 2200483 | G13: 2075178 | H13: 125305
... A106: Mrs. Kusum Lata | B106: 44498 | C106: 6th Floor | D106: OFFICE-55 | E106: 446.73 | F106: 2232000 | G106: 0 | H106: 2232000
A107: TOTAL | E107: 52151 | F107: 283554068 | G107: 228989291 | H107: 54564777

Sheet COP & MOF
B2: Cost of Project
B3: Particulars | C3: Incurred till date | D3: To be Incurred | E3: Total
B4: Land & Development cost | C4: 52.66 | D4: =E4-C4 -> 6.94 | E4: 59.6
B5: Approval & Other Charges | C5: 2.14 | D5: =E5-C5 -> 0 | E5: 2.14
B6: FAR & Add. Compensation | C6: 11.36 | D6: =E6-C6 -> 0 | E6: 11.36
B7: Lease Rent | C7: 5.32 | D7: =E7-C7 -> 0 | E7: 5.32
B8: Construction Cost | C8: 284.84 | D8: =E8-C8 -> 0 | E8: 284.84
B9: Other Indirect Cost | C9: 32.02 | D9: =E9-C9 -> 0.7 | E9: =32.02+0.7 -> 32.72
B10: Finance Charges | C10: =59.6 -> 59.6 | D10: =E10-C10 -> -59.6
B11: Administrative Cost | C11: 25.65 | D11: =E11-C11 -> 0.75 | E11: =25.65+0.75 -> 26.4
B12: Total | C12: =SUM(C4:C11) -> 473.59 | D12: =SUM(D4:D11) -> -51.21 | E12: =SUM(E4:E11) -> 422.38
B13: Means of Finance
B14: Promoter’s Contribution/Other Payables | C14: 10.84 | D14: =E14-C14 -> 0 | E14: 10.84
B15: Proposed Loan from ABFL | C15: 0 | D15: =E15-C15 -> 20 | E15: 20
B16: FDR with ICICI Bank | C16: -7 | D16: 0 | E16: -7
B17: Creditors | C17: 0.58 | D17: 0 | E17: 0.58
B18: Equipment Finance | C18: 0.47 | D18: =E18-C18 -> 0 | E18: 0.47
B19: Cancelled Units refund due | C19: 8.43 | D19: 0 | E19: 8.43
B20: Booking Money | C20: 460.27 | D20: =D12-D15 -> -71.21 | E20: =E12-E14-E15-E16-E17-E18-E19 -> 389.06
B21: Total | C21: =SUM(C14:C20) -> 473.59 | D21: =SUM(D14:D20) -> -51.21 | E21: =SUM(E14:E20) -> 422.38
C22: =C21-C12 -> 0 | D22: =D21-D12 -> 0 | E22: =E21-E12 -> 0

Sheet GST
B1: Beaver International India Pvt. Ltd.
B2: GST No. 09AABCB8172G1ZL
B3: Month | C3: Turnover(Cr.)
B4: 44228 | C4: 2.14
B5: 44256 | C5: 3.5
B6: 44287 | C6: 0.16
B7: 44317 | C7: 0.16
B8: 44348 | C8: 0.51
B9: 44378 | C9: 0.55
B10: 44409 | C10: 0.59
B11: 44440 | C11: 0.45
B12: 44470 | C12: 3.21
B13: 44501 | C13: 2.62
B14: 44531 | C14: 0.48
B15: 44562 | C15: 2.14
